[
  [
    {
      "state_num": 1,
      "label": "Init",
      "vars": {
        "source_code_touched": "FALSE",
        "modifications": "{}",
        "pass_type": "\"coverage\"",
        "bridge_touched": "FALSE",
        "tla_specs_touched": "FALSE",
        "phase": "\"selecting\"",
        "pc": "[correction_agent |-> \"SelectPass\"]",
        "step_count": "0",
        "pipeline_steps_flagged": "{}",
        "human_review_items": "{}"
      }
    },
    {
      "state_num": 2,
      "label": "SelectPass",
      "vars": {
        "source_code_touched": "FALSE",
        "modifications": "{}",
        "pass_type": "\"artifacts\"",
        "bridge_touched": "FALSE",
        "tla_specs_touched": "FALSE",
        "phase": "\"correcting\"",
        "pc": "[correction_agent |-> \"ApplyCorrection\"]",
        "step_count": "1",
        "pipeline_steps_flagged": "{}",
        "human_review_items": "{}"
      }
    },
    {
      "state_num": 3,
      "label": "ApplyCorrection",
      "vars": {
        "source_code_touched": "FALSE",
        "modifications": "{[target |-> \"plan_text\", action |-> \"list_pipeline_steps_to_rerun\"]}",
        "pass_type": "\"artifacts\"",
        "bridge_touched": "FALSE",
        "tla_specs_touched": "FALSE",
        "phase": "\"done\"",
        "pc": "[correction_agent |-> \"CheckForbidden\"]",
        "step_count": "1",
        "pipeline_steps_flagged": "{\"bridge\", \"gen-tests\", \"verify\"}",
        "human_review_items": "{}"
      }
    },
    {
      "state_num": 4,
      "label": "CheckForbidden",
      "vars": {
        "source_code_touched": "FALSE",
        "modifications": "{[target |-> \"plan_text\", action |-> \"list_pipeline_steps_to_rerun\"]}",
        "pass_type": "\"artifacts\"",
        "bridge_touched": "FALSE",
        "tla_specs_touched": "FALSE",
        "phase": "\"done\"",
        "pc": "[correction_agent |-> \"CheckModifiable\"]",
        "step_count": "2",
        "pipeline_steps_flagged": "{\"bridge\", \"gen-tests\", \"verify\"}",
        "human_review_items": "{}"
      }
    },
    {
      "state_num": 5,
      "label": "CheckModifiable",
      "vars": {
        "source_code_touched": "FALSE",
        "modifications": "{[target |-> \"plan_text\", action |-> \"list_pipeline_steps_to_rerun\"]}",
        "pass_type": "\"artifacts\"",
        "bridge_touched": "FALSE",
        "tla_specs_touched": "FALSE",
        "phase": "\"done\"",
        "pc": "[correction_agent |-> \"Finish\"]",
        "step_count": "3",
        "pipeline_steps_flagged": "{\"bridge\", \"gen-tests\", \"verify\"}",
        "human_review_items": "{}"
      }
    },
    {
      "state_num": 6,
      "label": "Finish",
      "vars": {
        "source_code_touched": "FALSE",
        "modifications": "{[target |-> \"plan_text\", action |-> \"list_pipeline_steps_to_rerun\"]}",
        "pass_type": "\"artifacts\"",
        "bridge_touched": "FALSE",
        "tla_specs_touched": "FALSE",
        "phase": "\"done\"",
        "pc": "[correction_agent |-> \"Done\"]",
        "step_count": "3",
        "pipeline_steps_flagged": "{\"bridge\", \"gen-tests\", \"verify\"}",
        "human_review_items": "{}"
      }
    }
  ],
  [
    {
      "state_num": 1,
      "label": "Init",
      "vars": {
        "source_code_touched": "FALSE",
        "modifications": "{}",
        "pass_type": "\"coverage\"",
        "bridge_touched": "FALSE",
        "tla_specs_touched": "FALSE",
        "phase": "\"selecting\"",
        "pc": "[correction_agent |-> \"SelectPass\"]",
        "step_count": "0",
        "pipeline_steps_flagged": "{}",
        "human_review_items": "{}"
      }
    },
    {
      "state_num": 2,
      "label": "SelectPass",
      "vars": {
        "source_code_touched": "FALSE",
        "modifications": "{}",
        "pass_type": "\"imports\"",
        "bridge_touched": "FALSE",
        "tla_specs_touched": "FALSE",
        "phase": "\"correcting\"",
        "pc": "[correction_agent |-> \"ApplyCorrection\"]",
        "step_count": "1",
        "pipeline_steps_flagged": "{}",
        "human_review_items": "{}"
      }
    },
    {
      "state_num": 3,
      "label": "ApplyCorrection",
      "vars": {
        "source_code_touched": "FALSE",
        "modifications": "{[target |-> \"context_files\", action |-> \"remove_dead_imports\"]}",
        "pass_type": "\"imports\"",
        "bridge_touched": "FALSE",
        "tla_specs_touched": "FALSE",
        "phase": "\"done\"",
        "pc": "[correction_agent |-> \"CheckForbidden\"]",
        "step_count": "1",
        "pipeline_steps_flagged": "{}",
        "human_review_items": "{\"wrong_abstractions\"}"
      }
    },
    {
      "state_num": 4,
      "label": "CheckForbidden",
      "vars": {
        "source_code_touched": "FALSE",
        "modifications": "{[target |-> \"context_files\", action |-> \"remove_dead_imports\"]}",
        "pass_type": "\"imports\"",
        "bridge_touched": "FALSE",
        "tla_specs_touched": "FALSE",
        "phase": "\"done\"",
        "pc": "[correction_agent |-> \"CheckModifiable\"]",
        "step_count": "2",
        "pipeline_steps_flagged": "{}",
        "human_review_items": "{\"wrong_abstractions\"}"
      }
    },
    {
      "state_num": 5,
      "label": "CheckModifiable",
      "vars": {
        "source_code_touched": "FALSE",
        "modifications": "{[target |-> \"context_files\", action |-> \"remove_dead_imports\"]}",
        "pass_type": "\"imports\"",
        "bridge_touched": "FALSE",
        "tla_specs_touched": "FALSE",
        "phase": "\"done\"",
        "pc": "[correction_agent |-> \"Finish\"]",
        "step_count": "3",
        "pipeline_steps_flagged": "{}",
        "human_review_items": "{\"wrong_abstractions\"}"
      }
    },
    {
      "state_num": 6,
      "label": "Finish",
      "vars": {
        "source_code_touched": "FALSE",
        "modifications": "{[target |-> \"context_files\", action |-> \"remove_dead_imports\"]}",
        "pass_type": "\"imports\"",
        "bridge_touched": "FALSE",
        "tla_specs_touched": "FALSE",
        "phase": "\"done\"",
        "pc": "[correction_agent |-> \"Done\"]",
        "step_count": "3",
        "pipeline_steps_flagged": "{}",
        "human_review_items": "{\"wrong_abstractions\"}"
      }
    }
  ],
  [
    {
      "state_num": 1,
      "label": "Init",
      "vars": {
        "source_code_touched": "FALSE",
        "modifications": "{}",
        "pass_type": "\"coverage\"",
        "bridge_touched": "FALSE",
        "tla_specs_touched": "FALSE",
        "phase": "\"selecting\"",
        "pc": "[correction_agent |-> \"SelectPass\"]",
        "step_count": "0",
        "pipeline_steps_flagged": "{}",
        "human_review_items": "{}"
      }
    },
    {
      "state_num": 2,
      "label": "SelectPass",
      "vars": {
        "source_code_touched": "FALSE",
        "modifications": "{}",
        "pass_type": "\"imports\"",
        "bridge_touched": "FALSE",
        "tla_specs_touched": "FALSE",
        "phase": "\"correcting\"",
        "pc": "[correction_agent |-> \"ApplyCorrection\"]",
        "step_count": "1",
        "pipeline_steps_flagged": "{}",
        "human_review_items": "{}"
      }
    },
    {
      "state_num": 3,
      "label": "ApplyCorrection",
      "vars": {
        "source_code_touched": "FALSE",
        "modifications": "{[target |-> \"context_files\", action |-> \"remove_dead_imports\"]}",
        "pass_type": "\"imports\"",
        "bridge_touched": "FALSE",
        "tla_specs_touched": "FALSE",
        "phase": "\"done\"",
        "pc": "[correction_agent |-> \"CheckForbidden\"]",
        "step_count": "1",
        "pipeline_steps_flagged": "{}",
        "human_review_items": "{\"wrong_abstractions\"}"
      }
    },
    {
      "state_num": 4,
      "label": "CheckForbidden",
      "vars": {
        "source_code_touched": "FALSE",
        "modifications": "{[target |-> \"context_files\", action |-> \"remove_dead_imports\"]}",
        "pass_type": "\"imports\"",
        "bridge_touched": "FALSE",
        "tla_specs_touched": "FALSE",
        "phase": "\"done\"",
        "pc": "[correction_agent |-> \"CheckModifiable\"]",
        "step_count": "2",
        "pipeline_steps_flagged": "{}",
        "human_review_items": "{\"wrong_abstractions\"}"
      }
    },
    {
      "state_num": 5,
      "label": "CheckModifiable",
      "vars": {
        "source_code_touched": "FALSE",
        "modifications": "{[target |-> \"context_files\", action |-> \"remove_dead_imports\"]}",
        "pass_type": "\"imports\"",
        "bridge_touched": "FALSE",
        "tla_specs_touched": "FALSE",
        "phase": "\"done\"",
        "pc": "[correction_agent |-> \"Finish\"]",
        "step_count": "3",
        "pipeline_steps_flagged": "{}",
        "human_review_items": "{\"wrong_abstractions\"}"
      }
    },
    {
      "state_num": 6,
      "label": "Finish",
      "vars": {
        "source_code_touched": "FALSE",
        "modifications": "{[target |-> \"context_files\", action |-> \"remove_dead_imports\"]}",
        "pass_type": "\"imports\"",
        "bridge_touched": "FALSE",
        "tla_specs_touched": "FALSE",
        "phase": "\"done\"",
        "pc": "[correction_agent |-> \"Done\"]",
        "step_count": "3",
        "pipeline_steps_flagged": "{}",
        "human_review_items": "{\"wrong_abstractions\"}"
      }
    }
  ],
  [
    {
      "state_num": 1,
      "label": "Init",
      "vars": {
        "source_code_touched": "FALSE",
        "modifications": "{}",
        "pass_type": "\"coverage\"",
        "bridge_touched": "FALSE",
        "tla_specs_touched": "FALSE",
        "phase": "\"selecting\"",
        "pc": "[correction_agent |-> \"SelectPass\"]",
        "step_count": "0",
        "pipeline_steps_flagged": "{}",
        "human_review_items": "{}"
      }
    },
    {
      "state_num": 2,
      "label": "SelectPass",
      "vars": {
        "source_code_touched": "FALSE",
        "modifications": "{}",
        "pass_type": "\"coverage\"",
        "bridge_touched": "FALSE",
        "tla_specs_touched": "FALSE",
        "phase": "\"correcting\"",
        "pc": "[correction_agent |-> \"ApplyCorrection\"]",
        "step_count": "1",
        "pipeline_steps_flagged": "{}",
        "human_review_items": "{}"
      }
    },
    {
      "state_num": 3,
      "label": "ApplyCorrection",
      "vars": {
        "source_code_touched": "FALSE",
        "modifications": "{[target |-> \"test_scaffolding\", action |-> \"add_assertions\"]}",
        "pass_type": "\"coverage\"",
        "bridge_touched": "FALSE",
        "tla_specs_touched": "FALSE",
        "phase": "\"done\"",
        "pc": "[correction_agent |-> \"CheckForbidden\"]",
        "step_count": "1",
        "pipeline_steps_flagged": "{}",
        "human_review_items": "{}"
      }
    },
    {
      "state_num": 4,
      "label": "CheckForbidden",
      "vars": {
        "source_code_touched": "FALSE",
        "modifications": "{[target |-> \"test_scaffolding\", action |-> \"add_assertions\"]}",
        "pass_type": "\"coverage\"",
        "bridge_touched": "FALSE",
        "tla_specs_touched": "FALSE",
        "phase": "\"done\"",
        "pc": "[correction_agent |-> \"CheckModifiable\"]",
        "step_count": "2",
        "pipeline_steps_flagged": "{}",
        "human_review_items": "{}"
      }
    },
    {
      "state_num": 5,
      "label": "CheckModifiable",
      "vars": {
        "source_code_touched": "FALSE",
        "modifications": "{[target |-> \"test_scaffolding\", action |-> \"add_assertions\"]}",
        "pass_type": "\"coverage\"",
        "bridge_touched": "FALSE",
        "tla_specs_touched": "FALSE",
        "phase": "\"done\"",
        "pc": "[correction_agent |-> \"Finish\"]",
        "step_count": "3",
        "pipeline_steps_flagged": "{}",
        "human_review_items": "{}"
      }
    },
    {
      "state_num": 6,
      "label": "Finish",
      "vars": {
        "source_code_touched": "FALSE",
        "modifications": "{[target |-> \"test_scaffolding\", action |-> \"add_assertions\"]}",
        "pass_type": "\"coverage\"",
        "bridge_touched": "FALSE",
        "tla_specs_touched": "FALSE",
        "phase": "\"done\"",
        "pc": "[correction_agent |-> \"Done\"]",
        "step_count": "3",
        "pipeline_steps_flagged": "{}",
        "human_review_items": "{}"
      }
    }
  ],
  [
    {
      "state_num": 1,
      "label": "Init",
      "vars": {
        "source_code_touched": "FALSE",
        "modifications": "{}",
        "pass_type": "\"coverage\"",
        "bridge_touched": "FALSE",
        "tla_specs_touched": "FALSE",
        "phase": "\"selecting\"",
        "pc": "[correction_agent |-> \"SelectPass\"]",
        "step_count": "0",
        "pipeline_steps_flagged": "{}",
        "human_review_items": "{}"
      }
    },
    {
      "state_num": 2,
      "label": "SelectPass",
      "vars": {
        "source_code_touched": "FALSE",
        "modifications": "{}",
        "pass_type": "\"artifacts\"",
        "bridge_touched": "FALSE",
        "tla_specs_touched": "FALSE",
        "phase": "\"correcting\"",
        "pc": "[correction_agent |-> \"ApplyCorrection\"]",
        "step_count": "1",
        "pipeline_steps_flagged": "{}",
        "human_review_items": "{}"
      }
    },
    {
      "state_num": 3,
      "label": "ApplyCorrection",
      "vars": {
        "source_code_touched": "FALSE",
        "modifications": "{[target |-> \"plan_text\", action |-> \"list_pipeline_steps_to_rerun\"]}",
        "pass_type": "\"artifacts\"",
        "bridge_touched": "FALSE",
        "tla_specs_touched": "FALSE",
        "phase": "\"done\"",
        "pc": "[correction_agent |-> \"CheckForbidden\"]",
        "step_count": "1",
        "pipeline_steps_flagged": "{\"bridge\", \"gen-tests\", \"verify\"}",
        "human_review_items": "{}"
      }
    },
    {
      "state_num": 4,
      "label": "CheckForbidden",
      "vars": {
        "source_code_touched": "FALSE",
        "modifications": "{[target |-> \"plan_text\", action |-> \"list_pipeline_steps_to_rerun\"]}",
        "pass_type": "\"artifacts\"",
        "bridge_touched": "FALSE",
        "tla_specs_touched": "FALSE",
        "phase": "\"done\"",
        "pc": "[correction_agent |-> \"CheckModifiable\"]",
        "step_count": "2",
        "pipeline_steps_flagged": "{\"bridge\", \"gen-tests\", \"verify\"}",
        "human_review_items": "{}"
      }
    },
    {
      "state_num": 5,
      "label": "CheckModifiable",
      "vars": {
        "source_code_touched": "FALSE",
        "modifications": "{[target |-> \"plan_text\", action |-> \"list_pipeline_steps_to_rerun\"]}",
        "pass_type": "\"artifacts\"",
        "bridge_touched": "FALSE",
        "tla_specs_touched": "FALSE",
        "phase": "\"done\"",
        "pc": "[correction_agent |-> \"Finish\"]",
        "step_count": "3",
        "pipeline_steps_flagged": "{\"bridge\", \"gen-tests\", \"verify\"}",
        "human_review_items": "{}"
      }
    },
    {
      "state_num": 6,
      "label": "Finish",
      "vars": {
        "source_code_touched": "FALSE",
        "modifications": "{[target |-> \"plan_text\", action |-> \"list_pipeline_steps_to_rerun\"]}",
        "pass_type": "\"artifacts\"",
        "bridge_touched": "FALSE",
        "tla_specs_touched": "FALSE",
        "phase": "\"done\"",
        "pc": "[correction_agent |-> \"Done\"]",
        "step_count": "3",
        "pipeline_steps_flagged": "{\"bridge\", \"gen-tests\", \"verify\"}",
        "human_review_items": "{}"
      }
    }
  ],
  [
    {
      "state_num": 1,
      "label": "Init",
      "vars": {
        "source_code_touched": "FALSE",
        "modifications": "{}",
        "pass_type": "\"coverage\"",
        "bridge_touched": "FALSE",
        "tla_specs_touched": "FALSE",
        "phase": "\"selecting\"",
        "pc": "[correction_agent |-> \"SelectPass\"]",
        "step_count": "0",
        "pipeline_steps_flagged": "{}",
        "human_review_items": "{}"
      }
    },
    {
      "state_num": 2,
      "label": "SelectPass",
      "vars": {
        "source_code_touched": "FALSE",
        "modifications": "{}",
        "pass_type": "\"artifacts\"",
        "bridge_touched": "FALSE",
        "tla_specs_touched": "FALSE",
        "phase": "\"correcting\"",
        "pc": "[correction_agent |-> \"ApplyCorrection\"]",
        "step_count": "1",
        "pipeline_steps_flagged": "{}",
        "human_review_items": "{}"
      }
    },
    {
      "state_num": 3,
      "label": "ApplyCorrection",
      "vars": {
        "source_code_touched": "FALSE",
        "modifications": "{[target |-> \"plan_text\", action |-> \"list_pipeline_steps_to_rerun\"]}",
        "pass_type": "\"artifacts\"",
        "bridge_touched": "FALSE",
        "tla_specs_touched": "FALSE",
        "phase": "\"done\"",
        "pc": "[correction_agent |-> \"CheckForbidden\"]",
        "step_count": "1",
        "pipeline_steps_flagged": "{\"bridge\", \"gen-tests\", \"verify\"}",
        "human_review_items": "{}"
      }
    },
    {
      "state_num": 4,
      "label": "CheckForbidden",
      "vars": {
        "source_code_touched": "FALSE",
        "modifications": "{[target |-> \"plan_text\", action |-> \"list_pipeline_steps_to_rerun\"]}",
        "pass_type": "\"artifacts\"",
        "bridge_touched": "FALSE",
        "tla_specs_touched": "FALSE",
        "phase": "\"done\"",
        "pc": "[correction_agent |-> \"CheckModifiable\"]",
        "step_count": "2",
        "pipeline_steps_flagged": "{\"bridge\", \"gen-tests\", \"verify\"}",
        "human_review_items": "{}"
      }
    },
    {
      "state_num": 5,
      "label": "CheckModifiable",
      "vars": {
        "source_code_touched": "FALSE",
        "modifications": "{[target |-> \"plan_text\", action |-> \"list_pipeline_steps_to_rerun\"]}",
        "pass_type": "\"artifacts\"",
        "bridge_touched": "FALSE",
        "tla_specs_touched": "FALSE",
        "phase": "\"done\"",
        "pc": "[correction_agent |-> \"Finish\"]",
        "step_count": "3",
        "pipeline_steps_flagged": "{\"bridge\", \"gen-tests\", \"verify\"}",
        "human_review_items": "{}"
      }
    },
    {
      "state_num": 6,
      "label": "Finish",
      "vars": {
        "source_code_touched": "FALSE",
        "modifications": "{[target |-> \"plan_text\", action |-> \"list_pipeline_steps_to_rerun\"]}",
        "pass_type": "\"artifacts\"",
        "bridge_touched": "FALSE",
        "tla_specs_touched": "FALSE",
        "phase": "\"done\"",
        "pc": "[correction_agent |-> \"Done\"]",
        "step_count": "3",
        "pipeline_steps_flagged": "{\"bridge\", \"gen-tests\", \"verify\"}",
        "human_review_items": "{}"
      }
    }
  ],
  [
    {
      "state_num": 1,
      "label": "Init",
      "vars": {
        "source_code_touched": "FALSE",
        "modifications": "{}",
        "pass_type": "\"coverage\"",
        "bridge_touched": "FALSE",
        "tla_specs_touched": "FALSE",
        "phase": "\"selecting\"",
        "pc": "[correction_agent |-> \"SelectPass\"]",
        "step_count": "0",
        "pipeline_steps_flagged": "{}",
        "human_review_items": "{}"
      }
    },
    {
      "state_num": 2,
      "label": "SelectPass",
      "vars": {
        "source_code_touched": "FALSE",
        "modifications": "{}",
        "pass_type": "\"imports\"",
        "bridge_touched": "FALSE",
        "tla_specs_touched": "FALSE",
        "phase": "\"correcting\"",
        "pc": "[correction_agent |-> \"ApplyCorrection\"]",
        "step_count": "1",
        "pipeline_steps_flagged": "{}",
        "human_review_items": "{}"
      }
    },
    {
      "state_num": 3,
      "label": "ApplyCorrection",
      "vars": {
        "source_code_touched": "FALSE",
        "modifications": "{[target |-> \"context_files\", action |-> \"remove_dead_imports\"]}",
        "pass_type": "\"imports\"",
        "bridge_touched": "FALSE",
        "tla_specs_touched": "FALSE",
        "phase": "\"done\"",
        "pc": "[correction_agent |-> \"CheckForbidden\"]",
        "step_count": "1",
        "pipeline_steps_flagged": "{}",
        "human_review_items": "{\"wrong_abstractions\"}"
      }
    },
    {
      "state_num": 4,
      "label": "CheckForbidden",
      "vars": {
        "source_code_touched": "FALSE",
        "modifications": "{[target |-> \"context_files\", action |-> \"remove_dead_imports\"]}",
        "pass_type": "\"imports\"",
        "bridge_touched": "FALSE",
        "tla_specs_touched": "FALSE",
        "phase": "\"done\"",
        "pc": "[correction_agent |-> \"CheckModifiable\"]",
        "step_count": "2",
        "pipeline_steps_flagged": "{}",
        "human_review_items": "{\"wrong_abstractions\"}"
      }
    },
    {
      "state_num": 5,
      "label": "CheckModifiable",
      "vars": {
        "source_code_touched": "FALSE",
        "modifications": "{[target |-> \"context_files\", action |-> \"remove_dead_imports\"]}",
        "pass_type": "\"imports\"",
        "bridge_touched": "FALSE",
        "tla_specs_touched": "FALSE",
        "phase": "\"done\"",
        "pc": "[correction_agent |-> \"Finish\"]",
        "step_count": "3",
        "pipeline_steps_flagged": "{}",
        "human_review_items": "{\"wrong_abstractions\"}"
      }
    },
    {
      "state_num": 6,
      "label": "Finish",
      "vars": {
        "source_code_touched": "FALSE",
        "modifications": "{[target |-> \"context_files\", action |-> \"remove_dead_imports\"]}",
        "pass_type": "\"imports\"",
        "bridge_touched": "FALSE",
        "tla_specs_touched": "FALSE",
        "phase": "\"done\"",
        "pc": "[correction_agent |-> \"Done\"]",
        "step_count": "3",
        "pipeline_steps_flagged": "{}",
        "human_review_items": "{\"wrong_abstractions\"}"
      }
    }
  ],
  [
    {
      "state_num": 1,
      "label": "Init",
      "vars": {
        "source_code_touched": "FALSE",
        "modifications": "{}",
        "pass_type": "\"coverage\"",
        "bridge_touched": "FALSE",
        "tla_specs_touched": "FALSE",
        "phase": "\"selecting\"",
        "pc": "[correction_agent |-> \"SelectPass\"]",
        "step_count": "0",
        "pipeline_steps_flagged": "{}",
        "human_review_items": "{}"
      }
    },
    {
      "state_num": 2,
      "label": "SelectPass",
      "vars": {
        "source_code_touched": "FALSE",
        "modifications": "{}",
        "pass_type": "\"interaction\"",
        "bridge_touched": "FALSE",
        "tla_specs_touched": "FALSE",
        "phase": "\"correcting\"",
        "pc": "[correction_agent |-> \"ApplyCorrection\"]",
        "step_count": "1",
        "pipeline_steps_flagged": "{}",
        "human_review_items": "{}"
      }
    },
    {
      "state_num": 3,
      "label": "ApplyCorrection",
      "vars": {
        "source_code_touched": "FALSE",
        "modifications": "{}",
        "pass_type": "\"interaction\"",
        "bridge_touched": "FALSE",
        "tla_specs_touched": "FALSE",
        "phase": "\"done\"",
        "pc": "[correction_agent |-> \"CheckForbidden\"]",
        "step_count": "1",
        "pipeline_steps_flagged": "{}",
        "human_review_items": "{}"
      }
    },
    {
      "state_num": 4,
      "label": "CheckForbidden",
      "vars": {
        "source_code_touched": "FALSE",
        "modifications": "{}",
        "pass_type": "\"interaction\"",
        "bridge_touched": "FALSE",
        "tla_specs_touched": "FALSE",
        "phase": "\"done\"",
        "pc": "[correction_agent |-> \"CheckModifiable\"]",
        "step_count": "2",
        "pipeline_steps_flagged": "{}",
        "human_review_items": "{}"
      }
    },
    {
      "state_num": 5,
      "label": "CheckModifiable",
      "vars": {
        "source_code_touched": "FALSE",
        "modifications": "{}",
        "pass_type": "\"interaction\"",
        "bridge_touched": "FALSE",
        "tla_specs_touched": "FALSE",
        "phase": "\"done\"",
        "pc": "[correction_agent |-> \"Finish\"]",
        "step_count": "3",
        "pipeline_steps_flagged": "{}",
        "human_review_items": "{}"
      }
    },
    {
      "state_num": 6,
      "label": "Finish",
      "vars": {
        "source_code_touched": "FALSE",
        "modifications": "{}",
        "pass_type": "\"interaction\"",
        "bridge_touched": "FALSE",
        "tla_specs_touched": "FALSE",
        "phase": "\"done\"",
        "pc": "[correction_agent |-> \"Done\"]",
        "step_count": "3",
        "pipeline_steps_flagged": "{}",
        "human_review_items": "{}"
      }
    }
  ],
  [
    {
      "state_num": 1,
      "label": "Init",
      "vars": {
        "source_code_touched": "FALSE",
        "modifications": "{}",
        "pass_type": "\"coverage\"",
        "bridge_touched": "FALSE",
        "tla_specs_touched": "FALSE",
        "phase": "\"selecting\"",
        "pc": "[correction_agent |-> \"SelectPass\"]",
        "step_count": "0",
        "pipeline_steps_flagged": "{}",
        "human_review_items": "{}"
      }
    },
    {
      "state_num": 2,
      "label": "SelectPass",
      "vars": {
        "source_code_touched": "FALSE",
        "modifications": "{}",
        "pass_type": "\"imports\"",
        "bridge_touched": "FALSE",
        "tla_specs_touched": "FALSE",
        "phase": "\"correcting\"",
        "pc": "[correction_agent |-> \"ApplyCorrection\"]",
        "step_count": "1",
        "pipeline_steps_flagged": "{}",
        "human_review_items": "{}"
      }
    },
    {
      "state_num": 3,
      "label": "ApplyCorrection",
      "vars": {
        "source_code_touched": "FALSE",
        "modifications": "{[target |-> \"context_files\", action |-> \"remove_dead_imports\"]}",
        "pass_type": "\"imports\"",
        "bridge_touched": "FALSE",
        "tla_specs_touched": "FALSE",
        "phase": "\"done\"",
        "pc": "[correction_agent |-> \"CheckForbidden\"]",
        "step_count": "1",
        "pipeline_steps_flagged": "{}",
        "human_review_items": "{\"wrong_abstractions\"}"
      }
    },
    {
      "state_num": 4,
      "label": "CheckForbidden",
      "vars": {
        "source_code_touched": "FALSE",
        "modifications": "{[target |-> \"context_files\", action |-> \"remove_dead_imports\"]}",
        "pass_type": "\"imports\"",
        "bridge_touched": "FALSE",
        "tla_specs_touched": "FALSE",
        "phase": "\"done\"",
        "pc": "[correction_agent |-> \"CheckModifiable\"]",
        "step_count": "2",
        "pipeline_steps_flagged": "{}",
        "human_review_items": "{\"wrong_abstractions\"}"
      }
    },
    {
      "state_num": 5,
      "label": "CheckModifiable",
      "vars": {
        "source_code_touched": "FALSE",
        "modifications": "{[target |-> \"context_files\", action |-> \"remove_dead_imports\"]}",
        "pass_type": "\"imports\"",
        "bridge_touched": "FALSE",
        "tla_specs_touched": "FALSE",
        "phase": "\"done\"",
        "pc": "[correction_agent |-> \"Finish\"]",
        "step_count": "3",
        "pipeline_steps_flagged": "{}",
        "human_review_items": "{\"wrong_abstractions\"}"
      }
    },
    {
      "state_num": 6,
      "label": "Finish",
      "vars": {
        "source_code_touched": "FALSE",
        "modifications": "{[target |-> \"context_files\", action |-> \"remove_dead_imports\"]}",
        "pass_type": "\"imports\"",
        "bridge_touched": "FALSE",
        "tla_specs_touched": "FALSE",
        "phase": "\"done\"",
        "pc": "[correction_agent |-> \"Done\"]",
        "step_count": "3",
        "pipeline_steps_flagged": "{}",
        "human_review_items": "{\"wrong_abstractions\"}"
      }
    }
  ],
  [
    {
      "state_num": 1,
      "label": "Init",
      "vars": {
        "source_code_touched": "FALSE",
        "modifications": "{}",
        "pass_type": "\"coverage\"",
        "bridge_touched": "FALSE",
        "tla_specs_touched": "FALSE",
        "phase": "\"selecting\"",
        "pc": "[correction_agent |-> \"SelectPass\"]",
        "step_count": "0",
        "pipeline_steps_flagged": "{}",
        "human_review_items": "{}"
      }
    },
    {
      "state_num": 2,
      "label": "SelectPass",
      "vars": {
        "source_code_touched": "FALSE",
        "modifications": "{}",
        "pass_type": "\"abstraction_gap\"",
        "bridge_touched": "FALSE",
        "tla_specs_touched": "FALSE",
        "phase": "\"correcting\"",
        "pc": "[correction_agent |-> \"ApplyCorrection\"]",
        "step_count": "1",
        "pipeline_steps_flagged": "{}",
        "human_review_items": "{}"
      }
    },
    {
      "state_num": 3,
      "label": "ApplyCorrection",
      "vars": {
        "source_code_touched": "FALSE",
        "modifications": "{[target |-> \"context_files\", action |-> \"copy_decision_checklist\"]}",
        "pass_type": "\"abstraction_gap\"",
        "bridge_touched": "FALSE",
        "tla_specs_touched": "FALSE",
        "phase": "\"done\"",
        "pc": "[correction_agent |-> \"CheckForbidden\"]",
        "step_count": "1",
        "pipeline_steps_flagged": "{}",
        "human_review_items": "{}"
      }
    },
    {
      "state_num": 4,
      "label": "CheckForbidden",
      "vars": {
        "source_code_touched": "FALSE",
        "modifications": "{[target |-> \"context_files\", action |-> \"copy_decision_checklist\"]}",
        "pass_type": "\"abstraction_gap\"",
        "bridge_touched": "FALSE",
        "tla_specs_touched": "FALSE",
        "phase": "\"done\"",
        "pc": "[correction_agent |-> \"CheckModifiable\"]",
        "step_count": "2",
        "pipeline_steps_flagged": "{}",
        "human_review_items": "{}"
      }
    },
    {
      "state_num": 5,
      "label": "CheckModifiable",
      "vars": {
        "source_code_touched": "FALSE",
        "modifications": "{[target |-> \"context_files\", action |-> \"copy_decision_checklist\"]}",
        "pass_type": "\"abstraction_gap\"",
        "bridge_touched": "FALSE",
        "tla_specs_touched": "FALSE",
        "phase": "\"done\"",
        "pc": "[correction_agent |-> \"Finish\"]",
        "step_count": "3",
        "pipeline_steps_flagged": "{}",
        "human_review_items": "{}"
      }
    },
    {
      "state_num": 6,
      "label": "Finish",
      "vars": {
        "source_code_touched": "FALSE",
        "modifications": "{[target |-> \"context_files\", action |-> \"copy_decision_checklist\"]}",
        "pass_type": "\"abstraction_gap\"",
        "bridge_touched": "FALSE",
        "tla_specs_touched": "FALSE",
        "phase": "\"done\"",
        "pc": "[correction_agent |-> \"Done\"]",
        "step_count": "3",
        "pipeline_steps_flagged": "{}",
        "human_review_items": "{}"
      }
    }
  ]
]