[
  [
    {
      "state_num": 1,
      "label": "Init",
      "vars": {
        "verdict": "[artifacts |-> \"pending\", coverage |-> \"pending\", abstraction_gap |-> \"pending\"]",
        "correctionInvoked": "[artifacts |-> FALSE, coverage |-> FALSE, abstraction_gap |-> FALSE]",
        "summaryStatus": "\"pending\"",
        "pc": "[orch |-> \"OrchestratorStart\"]",
        "autoFix": "TRUE"
      }
    },
    {
      "state_num": 2,
      "label": "OrchestratorStart",
      "vars": {
        "verdict": "[artifacts |-> \"pending\", coverage |-> \"pending\", abstraction_gap |-> \"pending\"]",
        "correctionInvoked": "[artifacts |-> FALSE, coverage |-> FALSE, abstraction_gap |-> FALSE]",
        "summaryStatus": "\"pending\"",
        "pc": "[orch |-> \"SelectPass\"]",
        "autoFix": "TRUE"
      }
    },
    {
      "state_num": 3,
      "label": "SelectPass",
      "vars": {
        "verdict": "[artifacts |-> \"FAIL\", coverage |-> \"pending\", abstraction_gap |-> \"pending\"]",
        "correctionInvoked": "[artifacts |-> TRUE, coverage |-> FALSE, abstraction_gap |-> FALSE]",
        "summaryStatus": "\"pending\"",
        "pc": "[orch |-> \"OrchestratorStart\"]",
        "autoFix": "TRUE"
      }
    },
    {
      "state_num": 4,
      "label": "OrchestratorStart",
      "vars": {
        "verdict": "[artifacts |-> \"FAIL\", coverage |-> \"pending\", abstraction_gap |-> \"pending\"]",
        "correctionInvoked": "[artifacts |-> TRUE, coverage |-> FALSE, abstraction_gap |-> FALSE]",
        "summaryStatus": "\"pending\"",
        "pc": "[orch |-> \"ComputeSummary\"]",
        "autoFix": "TRUE"
      }
    },
    {
      "state_num": 5,
      "label": "ComputeSummary",
      "vars": {
        "verdict": "[artifacts |-> \"FAIL\", coverage |-> \"pending\", abstraction_gap |-> \"pending\"]",
        "correctionInvoked": "[artifacts |-> TRUE, coverage |-> FALSE, abstraction_gap |-> FALSE]",
        "summaryStatus": "\"fail\"",
        "pc": "[orch |-> \"Finish\"]",
        "autoFix": "TRUE"
      }
    },
    {
      "state_num": 6,
      "label": "Finish",
      "vars": {
        "verdict": "[artifacts |-> \"FAIL\", coverage |-> \"pending\", abstraction_gap |-> \"pending\"]",
        "correctionInvoked": "[artifacts |-> TRUE, coverage |-> FALSE, abstraction_gap |-> FALSE]",
        "summaryStatus": "\"fail\"",
        "pc": "[orch |-> \"Done\"]",
        "autoFix": "TRUE"
      }
    }
  ],
  [
    {
      "state_num": 1,
      "label": "Init",
      "vars": {
        "verdict": "[artifacts |-> \"pending\", coverage |-> \"pending\", abstraction_gap |-> \"pending\"]",
        "correctionInvoked": "[artifacts |-> FALSE, coverage |-> FALSE, abstraction_gap |-> FALSE]",
        "summaryStatus": "\"pending\"",
        "pc": "[orch |-> \"OrchestratorStart\"]",
        "autoFix": "TRUE"
      }
    },
    {
      "state_num": 2,
      "label": "OrchestratorStart",
      "vars": {
        "verdict": "[artifacts |-> \"pending\", coverage |-> \"pending\", abstraction_gap |-> \"pending\"]",
        "correctionInvoked": "[artifacts |-> FALSE, coverage |-> FALSE, abstraction_gap |-> FALSE]",
        "summaryStatus": "\"pending\"",
        "pc": "[orch |-> \"SelectPass\"]",
        "autoFix": "TRUE"
      }
    },
    {
      "state_num": 3,
      "label": "SelectPass",
      "vars": {
        "verdict": "[artifacts |-> \"WARNING\", coverage |-> \"pending\", abstraction_gap |-> \"pending\"]",
        "correctionInvoked": "[artifacts |-> FALSE, coverage |-> FALSE, abstraction_gap |-> FALSE]",
        "summaryStatus": "\"pending\"",
        "pc": "[orch |-> \"OrchestratorStart\"]",
        "autoFix": "TRUE"
      }
    },
    {
      "state_num": 4,
      "label": "OrchestratorStart",
      "vars": {
        "verdict": "[artifacts |-> \"WARNING\", coverage |-> \"pending\", abstraction_gap |-> \"pending\"]",
        "correctionInvoked": "[artifacts |-> FALSE, coverage |-> FALSE, abstraction_gap |-> FALSE]",
        "summaryStatus": "\"pending\"",
        "pc": "[orch |-> \"SelectPass\"]",
        "autoFix": "TRUE"
      }
    },
    {
      "state_num": 5,
      "label": "SelectPass",
      "vars": {
        "verdict": "[artifacts |-> \"WARNING\", coverage |-> \"PASS\", abstraction_gap |-> \"pending\"]",
        "correctionInvoked": "[artifacts |-> FALSE, coverage |-> FALSE, abstraction_gap |-> FALSE]",
        "summaryStatus": "\"pending\"",
        "pc": "[orch |-> \"OrchestratorStart\"]",
        "autoFix": "TRUE"
      }
    },
    {
      "state_num": 6,
      "label": "OrchestratorStart",
      "vars": {
        "verdict": "[artifacts |-> \"WARNING\", coverage |-> \"PASS\", abstraction_gap |-> \"pending\"]",
        "correctionInvoked": "[artifacts |-> FALSE, coverage |-> FALSE, abstraction_gap |-> FALSE]",
        "summaryStatus": "\"pending\"",
        "pc": "[orch |-> \"SelectPass\"]",
        "autoFix": "TRUE"
      }
    },
    {
      "state_num": 7,
      "label": "SelectPass",
      "vars": {
        "verdict": "[artifacts |-> \"WARNING\", coverage |-> \"PASS\", abstraction_gap |-> \"WARNING\"]",
        "correctionInvoked": "[artifacts |-> FALSE, coverage |-> FALSE, abstraction_gap |-> FALSE]",
        "summaryStatus": "\"pending\"",
        "pc": "[orch |-> \"OrchestratorStart\"]",
        "autoFix": "TRUE"
      }
    },
    {
      "state_num": 8,
      "label": "OrchestratorStart",
      "vars": {
        "verdict": "[artifacts |-> \"WARNING\", coverage |-> \"PASS\", abstraction_gap |-> \"WARNING\"]",
        "correctionInvoked": "[artifacts |-> FALSE, coverage |-> FALSE, abstraction_gap |-> FALSE]",
        "summaryStatus": "\"pending\"",
        "pc": "[orch |-> \"ComputeSummary\"]",
        "autoFix": "TRUE"
      }
    },
    {
      "state_num": 9,
      "label": "ComputeSummary",
      "vars": {
        "verdict": "[artifacts |-> \"WARNING\", coverage |-> \"PASS\", abstraction_gap |-> \"WARNING\"]",
        "correctionInvoked": "[artifacts |-> FALSE, coverage |-> FALSE, abstraction_gap |-> FALSE]",
        "summaryStatus": "\"warning\"",
        "pc": "[orch |-> \"Finish\"]",
        "autoFix": "TRUE"
      }
    },
    {
      "state_num": 10,
      "label": "Finish",
      "vars": {
        "verdict": "[artifacts |-> \"WARNING\", coverage |-> \"PASS\", abstraction_gap |-> \"WARNING\"]",
        "correctionInvoked": "[artifacts |-> FALSE, coverage |-> FALSE, abstraction_gap |-> FALSE]",
        "summaryStatus": "\"warning\"",
        "pc": "[orch |-> \"Done\"]",
        "autoFix": "TRUE"
      }
    }
  ],
  [
    {
      "state_num": 1,
      "label": "Init",
      "vars": {
        "verdict": "[artifacts |-> \"pending\", coverage |-> \"pending\", abstraction_gap |-> \"pending\"]",
        "correctionInvoked": "[artifacts |-> FALSE, coverage |-> FALSE, abstraction_gap |-> FALSE]",
        "summaryStatus": "\"pending\"",
        "pc": "[orch |-> \"OrchestratorStart\"]",
        "autoFix": "TRUE"
      }
    },
    {
      "state_num": 2,
      "label": "OrchestratorStart",
      "vars": {
        "verdict": "[artifacts |-> \"pending\", coverage |-> \"pending\", abstraction_gap |-> \"pending\"]",
        "correctionInvoked": "[artifacts |-> FALSE, coverage |-> FALSE, abstraction_gap |-> FALSE]",
        "summaryStatus": "\"pending\"",
        "pc": "[orch |-> \"SelectPass\"]",
        "autoFix": "TRUE"
      }
    },
    {
      "state_num": 3,
      "label": "SelectPass",
      "vars": {
        "verdict": "[artifacts |-> \"FAIL\", coverage |-> \"pending\", abstraction_gap |-> \"pending\"]",
        "correctionInvoked": "[artifacts |-> TRUE, coverage |-> FALSE, abstraction_gap |-> FALSE]",
        "summaryStatus": "\"pending\"",
        "pc": "[orch |-> \"OrchestratorStart\"]",
        "autoFix": "TRUE"
      }
    },
    {
      "state_num": 4,
      "label": "OrchestratorStart",
      "vars": {
        "verdict": "[artifacts |-> \"FAIL\", coverage |-> \"pending\", abstraction_gap |-> \"pending\"]",
        "correctionInvoked": "[artifacts |-> TRUE, coverage |-> FALSE, abstraction_gap |-> FALSE]",
        "summaryStatus": "\"pending\"",
        "pc": "[orch |-> \"ComputeSummary\"]",
        "autoFix": "TRUE"
      }
    },
    {
      "state_num": 5,
      "label": "ComputeSummary",
      "vars": {
        "verdict": "[artifacts |-> \"FAIL\", coverage |-> \"pending\", abstraction_gap |-> \"pending\"]",
        "correctionInvoked": "[artifacts |-> TRUE, coverage |-> FALSE, abstraction_gap |-> FALSE]",
        "summaryStatus": "\"fail\"",
        "pc": "[orch |-> \"Finish\"]",
        "autoFix": "TRUE"
      }
    },
    {
      "state_num": 6,
      "label": "Finish",
      "vars": {
        "verdict": "[artifacts |-> \"FAIL\", coverage |-> \"pending\", abstraction_gap |-> \"pending\"]",
        "correctionInvoked": "[artifacts |-> TRUE, coverage |-> FALSE, abstraction_gap |-> FALSE]",
        "summaryStatus": "\"fail\"",
        "pc": "[orch |-> \"Done\"]",
        "autoFix": "TRUE"
      }
    }
  ],
  [
    {
      "state_num": 1,
      "label": "Init",
      "vars": {
        "verdict": "[artifacts |-> \"pending\", coverage |-> \"pending\", abstraction_gap |-> \"pending\"]",
        "correctionInvoked": "[artifacts |-> FALSE, coverage |-> FALSE, abstraction_gap |-> FALSE]",
        "summaryStatus": "\"pending\"",
        "pc": "[orch |-> \"OrchestratorStart\"]",
        "autoFix": "TRUE"
      }
    },
    {
      "state_num": 2,
      "label": "OrchestratorStart",
      "vars": {
        "verdict": "[artifacts |-> \"pending\", coverage |-> \"pending\", abstraction_gap |-> \"pending\"]",
        "correctionInvoked": "[artifacts |-> FALSE, coverage |-> FALSE, abstraction_gap |-> FALSE]",
        "summaryStatus": "\"pending\"",
        "pc": "[orch |-> \"SelectPass\"]",
        "autoFix": "TRUE"
      }
    },
    {
      "state_num": 3,
      "label": "SelectPass",
      "vars": {
        "verdict": "[artifacts |-> \"WARNING\", coverage |-> \"pending\", abstraction_gap |-> \"pending\"]",
        "correctionInvoked": "[artifacts |-> FALSE, coverage |-> FALSE, abstraction_gap |-> FALSE]",
        "summaryStatus": "\"pending\"",
        "pc": "[orch |-> \"OrchestratorStart\"]",
        "autoFix": "TRUE"
      }
    },
    {
      "state_num": 4,
      "label": "OrchestratorStart",
      "vars": {
        "verdict": "[artifacts |-> \"WARNING\", coverage |-> \"pending\", abstraction_gap |-> \"pending\"]",
        "correctionInvoked": "[artifacts |-> FALSE, coverage |-> FALSE, abstraction_gap |-> FALSE]",
        "summaryStatus": "\"pending\"",
        "pc": "[orch |-> \"SelectPass\"]",
        "autoFix": "TRUE"
      }
    },
    {
      "state_num": 5,
      "label": "SelectPass",
      "vars": {
        "verdict": "[artifacts |-> \"WARNING\", coverage |-> \"PASS\", abstraction_gap |-> \"pending\"]",
        "correctionInvoked": "[artifacts |-> FALSE, coverage |-> FALSE, abstraction_gap |-> FALSE]",
        "summaryStatus": "\"pending\"",
        "pc": "[orch |-> \"OrchestratorStart\"]",
        "autoFix": "TRUE"
      }
    },
    {
      "state_num": 6,
      "label": "OrchestratorStart",
      "vars": {
        "verdict": "[artifacts |-> \"WARNING\", coverage |-> \"PASS\", abstraction_gap |-> \"pending\"]",
        "correctionInvoked": "[artifacts |-> FALSE, coverage |-> FALSE, abstraction_gap |-> FALSE]",
        "summaryStatus": "\"pending\"",
        "pc": "[orch |-> \"SelectPass\"]",
        "autoFix": "TRUE"
      }
    },
    {
      "state_num": 7,
      "label": "SelectPass",
      "vars": {
        "verdict": "[artifacts |-> \"WARNING\", coverage |-> \"PASS\", abstraction_gap |-> \"WARNING\"]",
        "correctionInvoked": "[artifacts |-> FALSE, coverage |-> FALSE, abstraction_gap |-> FALSE]",
        "summaryStatus": "\"pending\"",
        "pc": "[orch |-> \"OrchestratorStart\"]",
        "autoFix": "TRUE"
      }
    },
    {
      "state_num": 8,
      "label": "OrchestratorStart",
      "vars": {
        "verdict": "[artifacts |-> \"WARNING\", coverage |-> \"PASS\", abstraction_gap |-> \"WARNING\"]",
        "correctionInvoked": "[artifacts |-> FALSE, coverage |-> FALSE, abstraction_gap |-> FALSE]",
        "summaryStatus": "\"pending\"",
        "pc": "[orch |-> \"ComputeSummary\"]",
        "autoFix": "TRUE"
      }
    },
    {
      "state_num": 9,
      "label": "ComputeSummary",
      "vars": {
        "verdict": "[artifacts |-> \"WARNING\", coverage |-> \"PASS\", abstraction_gap |-> \"WARNING\"]",
        "correctionInvoked": "[artifacts |-> FALSE, coverage |-> FALSE, abstraction_gap |-> FALSE]",
        "summaryStatus": "\"warning\"",
        "pc": "[orch |-> \"Finish\"]",
        "autoFix": "TRUE"
      }
    },
    {
      "state_num": 10,
      "label": "Finish",
      "vars": {
        "verdict": "[artifacts |-> \"WARNING\", coverage |-> \"PASS\", abstraction_gap |-> \"WARNING\"]",
        "correctionInvoked": "[artifacts |-> FALSE, coverage |-> FALSE, abstraction_gap |-> FALSE]",
        "summaryStatus": "\"warning\"",
        "pc": "[orch |-> \"Done\"]",
        "autoFix": "TRUE"
      }
    }
  ],
  [
    {
      "state_num": 1,
      "label": "Init",
      "vars": {
        "verdict": "[artifacts |-> \"pending\", coverage |-> \"pending\", abstraction_gap |-> \"pending\"]",
        "correctionInvoked": "[artifacts |-> FALSE, coverage |-> FALSE, abstraction_gap |-> FALSE]",
        "summaryStatus": "\"pending\"",
        "pc": "[orch |-> \"OrchestratorStart\"]",
        "autoFix": "TRUE"
      }
    },
    {
      "state_num": 2,
      "label": "OrchestratorStart",
      "vars": {
        "verdict": "[artifacts |-> \"pending\", coverage |-> \"pending\", abstraction_gap |-> \"pending\"]",
        "correctionInvoked": "[artifacts |-> FALSE, coverage |-> FALSE, abstraction_gap |-> FALSE]",
        "summaryStatus": "\"pending\"",
        "pc": "[orch |-> \"SelectPass\"]",
        "autoFix": "TRUE"
      }
    },
    {
      "state_num": 3,
      "label": "SelectPass",
      "vars": {
        "verdict": "[artifacts |-> \"WARNING\", coverage |-> \"pending\", abstraction_gap |-> \"pending\"]",
        "correctionInvoked": "[artifacts |-> FALSE, coverage |-> FALSE, abstraction_gap |-> FALSE]",
        "summaryStatus": "\"pending\"",
        "pc": "[orch |-> \"OrchestratorStart\"]",
        "autoFix": "TRUE"
      }
    },
    {
      "state_num": 4,
      "label": "OrchestratorStart",
      "vars": {
        "verdict": "[artifacts |-> \"WARNING\", coverage |-> \"pending\", abstraction_gap |-> \"pending\"]",
        "correctionInvoked": "[artifacts |-> FALSE, coverage |-> FALSE, abstraction_gap |-> FALSE]",
        "summaryStatus": "\"pending\"",
        "pc": "[orch |-> \"SelectPass\"]",
        "autoFix": "TRUE"
      }
    },
    {
      "state_num": 5,
      "label": "SelectPass",
      "vars": {
        "verdict": "[artifacts |-> \"WARNING\", coverage |-> \"PASS\", abstraction_gap |-> \"pending\"]",
        "correctionInvoked": "[artifacts |-> FALSE, coverage |-> FALSE, abstraction_gap |-> FALSE]",
        "summaryStatus": "\"pending\"",
        "pc": "[orch |-> \"OrchestratorStart\"]",
        "autoFix": "TRUE"
      }
    },
    {
      "state_num": 6,
      "label": "OrchestratorStart",
      "vars": {
        "verdict": "[artifacts |-> \"WARNING\", coverage |-> \"PASS\", abstraction_gap |-> \"pending\"]",
        "correctionInvoked": "[artifacts |-> FALSE, coverage |-> FALSE, abstraction_gap |-> FALSE]",
        "summaryStatus": "\"pending\"",
        "pc": "[orch |-> \"SelectPass\"]",
        "autoFix": "TRUE"
      }
    },
    {
      "state_num": 7,
      "label": "SelectPass",
      "vars": {
        "verdict": "[artifacts |-> \"WARNING\", coverage |-> \"PASS\", abstraction_gap |-> \"PASS\"]",
        "correctionInvoked": "[artifacts |-> FALSE, coverage |-> FALSE, abstraction_gap |-> FALSE]",
        "summaryStatus": "\"pending\"",
        "pc": "[orch |-> \"OrchestratorStart\"]",
        "autoFix": "TRUE"
      }
    },
    {
      "state_num": 8,
      "label": "OrchestratorStart",
      "vars": {
        "verdict": "[artifacts |-> \"WARNING\", coverage |-> \"PASS\", abstraction_gap |-> \"PASS\"]",
        "correctionInvoked": "[artifacts |-> FALSE, coverage |-> FALSE, abstraction_gap |-> FALSE]",
        "summaryStatus": "\"pending\"",
        "pc": "[orch |-> \"ComputeSummary\"]",
        "autoFix": "TRUE"
      }
    },
    {
      "state_num": 9,
      "label": "ComputeSummary",
      "vars": {
        "verdict": "[artifacts |-> \"WARNING\", coverage |-> \"PASS\", abstraction_gap |-> \"PASS\"]",
        "correctionInvoked": "[artifacts |-> FALSE, coverage |-> FALSE, abstraction_gap |-> FALSE]",
        "summaryStatus": "\"warning\"",
        "pc": "[orch |-> \"Finish\"]",
        "autoFix": "TRUE"
      }
    },
    {
      "state_num": 10,
      "label": "Finish",
      "vars": {
        "verdict": "[artifacts |-> \"WARNING\", coverage |-> \"PASS\", abstraction_gap |-> \"PASS\"]",
        "correctionInvoked": "[artifacts |-> FALSE, coverage |-> FALSE, abstraction_gap |-> FALSE]",
        "summaryStatus": "\"warning\"",
        "pc": "[orch |-> \"Done\"]",
        "autoFix": "TRUE"
      }
    }
  ],
  [
    {
      "state_num": 1,
      "label": "Init",
      "vars": {
        "verdict": "[artifacts |-> \"pending\", coverage |-> \"pending\", abstraction_gap |-> \"pending\"]",
        "correctionInvoked": "[artifacts |-> FALSE, coverage |-> FALSE, abstraction_gap |-> FALSE]",
        "summaryStatus": "\"pending\"",
        "pc": "[orch |-> \"OrchestratorStart\"]",
        "autoFix": "TRUE"
      }
    },
    {
      "state_num": 2,
      "label": "OrchestratorStart",
      "vars": {
        "verdict": "[artifacts |-> \"pending\", coverage |-> \"pending\", abstraction_gap |-> \"pending\"]",
        "correctionInvoked": "[artifacts |-> FALSE, coverage |-> FALSE, abstraction_gap |-> FALSE]",
        "summaryStatus": "\"pending\"",
        "pc": "[orch |-> \"SelectPass\"]",
        "autoFix": "TRUE"
      }
    },
    {
      "state_num": 3,
      "label": "SelectPass",
      "vars": {
        "verdict": "[artifacts |-> \"PASS\", coverage |-> \"pending\", abstraction_gap |-> \"pending\"]",
        "correctionInvoked": "[artifacts |-> FALSE, coverage |-> FALSE, abstraction_gap |-> FALSE]",
        "summaryStatus": "\"pending\"",
        "pc": "[orch |-> \"OrchestratorStart\"]",
        "autoFix": "TRUE"
      }
    },
    {
      "state_num": 4,
      "label": "OrchestratorStart",
      "vars": {
        "verdict": "[artifacts |-> \"PASS\", coverage |-> \"pending\", abstraction_gap |-> \"pending\"]",
        "correctionInvoked": "[artifacts |-> FALSE, coverage |-> FALSE, abstraction_gap |-> FALSE]",
        "summaryStatus": "\"pending\"",
        "pc": "[orch |-> \"SelectPass\"]",
        "autoFix": "TRUE"
      }
    },
    {
      "state_num": 5,
      "label": "SelectPass",
      "vars": {
        "verdict": "[artifacts |-> \"PASS\", coverage |-> \"WARNING\", abstraction_gap |-> \"pending\"]",
        "correctionInvoked": "[artifacts |-> FALSE, coverage |-> FALSE, abstraction_gap |-> FALSE]",
        "summaryStatus": "\"pending\"",
        "pc": "[orch |-> \"OrchestratorStart\"]",
        "autoFix": "TRUE"
      }
    },
    {
      "state_num": 6,
      "label": "OrchestratorStart",
      "vars": {
        "verdict": "[artifacts |-> \"PASS\", coverage |-> \"WARNING\", abstraction_gap |-> \"pending\"]",
        "correctionInvoked": "[artifacts |-> FALSE, coverage |-> FALSE, abstraction_gap |-> FALSE]",
        "summaryStatus": "\"pending\"",
        "pc": "[orch |-> \"SelectPass\"]",
        "autoFix": "TRUE"
      }
    },
    {
      "state_num": 7,
      "label": "SelectPass",
      "vars": {
        "verdict": "[artifacts |-> \"PASS\", coverage |-> \"WARNING\", abstraction_gap |-> \"PASS\"]",
        "correctionInvoked": "[artifacts |-> FALSE, coverage |-> FALSE, abstraction_gap |-> FALSE]",
        "summaryStatus": "\"pending\"",
        "pc": "[orch |-> \"OrchestratorStart\"]",
        "autoFix": "TRUE"
      }
    },
    {
      "state_num": 8,
      "label": "OrchestratorStart",
      "vars": {
        "verdict": "[artifacts |-> \"PASS\", coverage |-> \"WARNING\", abstraction_gap |-> \"PASS\"]",
        "correctionInvoked": "[artifacts |-> FALSE, coverage |-> FALSE, abstraction_gap |-> FALSE]",
        "summaryStatus": "\"pending\"",
        "pc": "[orch |-> \"ComputeSummary\"]",
        "autoFix": "TRUE"
      }
    },
    {
      "state_num": 9,
      "label": "ComputeSummary",
      "vars": {
        "verdict": "[artifacts |-> \"PASS\", coverage |-> \"WARNING\", abstraction_gap |-> \"PASS\"]",
        "correctionInvoked": "[artifacts |-> FALSE, coverage |-> FALSE, abstraction_gap |-> FALSE]",
        "summaryStatus": "\"warning\"",
        "pc": "[orch |-> \"Finish\"]",
        "autoFix": "TRUE"
      }
    },
    {
      "state_num": 10,
      "label": "Finish",
      "vars": {
        "verdict": "[artifacts |-> \"PASS\", coverage |-> \"WARNING\", abstraction_gap |-> \"PASS\"]",
        "correctionInvoked": "[artifacts |-> FALSE, coverage |-> FALSE, abstraction_gap |-> FALSE]",
        "summaryStatus": "\"warning\"",
        "pc": "[orch |-> \"Done\"]",
        "autoFix": "TRUE"
      }
    }
  ],
  [
    {
      "state_num": 1,
      "label": "Init",
      "vars": {
        "verdict": "[artifacts |-> \"pending\", coverage |-> \"pending\", abstraction_gap |-> \"pending\"]",
        "correctionInvoked": "[artifacts |-> FALSE, coverage |-> FALSE, abstraction_gap |-> FALSE]",
        "summaryStatus": "\"pending\"",
        "pc": "[orch |-> \"OrchestratorStart\"]",
        "autoFix": "TRUE"
      }
    },
    {
      "state_num": 2,
      "label": "OrchestratorStart",
      "vars": {
        "verdict": "[artifacts |-> \"pending\", coverage |-> \"pending\", abstraction_gap |-> \"pending\"]",
        "correctionInvoked": "[artifacts |-> FALSE, coverage |-> FALSE, abstraction_gap |-> FALSE]",
        "summaryStatus": "\"pending\"",
        "pc": "[orch |-> \"SelectPass\"]",
        "autoFix": "TRUE"
      }
    },
    {
      "state_num": 3,
      "label": "SelectPass",
      "vars": {
        "verdict": "[artifacts |-> \"FAIL\", coverage |-> \"pending\", abstraction_gap |-> \"pending\"]",
        "correctionInvoked": "[artifacts |-> TRUE, coverage |-> FALSE, abstraction_gap |-> FALSE]",
        "summaryStatus": "\"pending\"",
        "pc": "[orch |-> \"OrchestratorStart\"]",
        "autoFix": "TRUE"
      }
    },
    {
      "state_num": 4,
      "label": "OrchestratorStart",
      "vars": {
        "verdict": "[artifacts |-> \"FAIL\", coverage |-> \"pending\", abstraction_gap |-> \"pending\"]",
        "correctionInvoked": "[artifacts |-> TRUE, coverage |-> FALSE, abstraction_gap |-> FALSE]",
        "summaryStatus": "\"pending\"",
        "pc": "[orch |-> \"ComputeSummary\"]",
        "autoFix": "TRUE"
      }
    },
    {
      "state_num": 5,
      "label": "ComputeSummary",
      "vars": {
        "verdict": "[artifacts |-> \"FAIL\", coverage |-> \"pending\", abstraction_gap |-> \"pending\"]",
        "correctionInvoked": "[artifacts |-> TRUE, coverage |-> FALSE, abstraction_gap |-> FALSE]",
        "summaryStatus": "\"fail\"",
        "pc": "[orch |-> \"Finish\"]",
        "autoFix": "TRUE"
      }
    },
    {
      "state_num": 6,
      "label": "Finish",
      "vars": {
        "verdict": "[artifacts |-> \"FAIL\", coverage |-> \"pending\", abstraction_gap |-> \"pending\"]",
        "correctionInvoked": "[artifacts |-> TRUE, coverage |-> FALSE, abstraction_gap |-> FALSE]",
        "summaryStatus": "\"fail\"",
        "pc": "[orch |-> \"Done\"]",
        "autoFix": "TRUE"
      }
    }
  ],
  [
    {
      "state_num": 1,
      "label": "Init",
      "vars": {
        "verdict": "[artifacts |-> \"pending\", coverage |-> \"pending\", abstraction_gap |-> \"pending\"]",
        "correctionInvoked": "[artifacts |-> FALSE, coverage |-> FALSE, abstraction_gap |-> FALSE]",
        "summaryStatus": "\"pending\"",
        "pc": "[orch |-> \"OrchestratorStart\"]",
        "autoFix": "TRUE"
      }
    },
    {
      "state_num": 2,
      "label": "OrchestratorStart",
      "vars": {
        "verdict": "[artifacts |-> \"pending\", coverage |-> \"pending\", abstraction_gap |-> \"pending\"]",
        "correctionInvoked": "[artifacts |-> FALSE, coverage |-> FALSE, abstraction_gap |-> FALSE]",
        "summaryStatus": "\"pending\"",
        "pc": "[orch |-> \"SelectPass\"]",
        "autoFix": "TRUE"
      }
    },
    {
      "state_num": 3,
      "label": "SelectPass",
      "vars": {
        "verdict": "[artifacts |-> \"PASS\", coverage |-> \"pending\", abstraction_gap |-> \"pending\"]",
        "correctionInvoked": "[artifacts |-> FALSE, coverage |-> FALSE, abstraction_gap |-> FALSE]",
        "summaryStatus": "\"pending\"",
        "pc": "[orch |-> \"OrchestratorStart\"]",
        "autoFix": "TRUE"
      }
    },
    {
      "state_num": 4,
      "label": "OrchestratorStart",
      "vars": {
        "verdict": "[artifacts |-> \"PASS\", coverage |-> \"pending\", abstraction_gap |-> \"pending\"]",
        "correctionInvoked": "[artifacts |-> FALSE, coverage |-> FALSE, abstraction_gap |-> FALSE]",
        "summaryStatus": "\"pending\"",
        "pc": "[orch |-> \"SelectPass\"]",
        "autoFix": "TRUE"
      }
    },
    {
      "state_num": 5,
      "label": "SelectPass",
      "vars": {
        "verdict": "[artifacts |-> \"PASS\", coverage |-> \"PASS\", abstraction_gap |-> \"pending\"]",
        "correctionInvoked": "[artifacts |-> FALSE, coverage |-> FALSE, abstraction_gap |-> FALSE]",
        "summaryStatus": "\"pending\"",
        "pc": "[orch |-> \"OrchestratorStart\"]",
        "autoFix": "TRUE"
      }
    },
    {
      "state_num": 6,
      "label": "OrchestratorStart",
      "vars": {
        "verdict": "[artifacts |-> \"PASS\", coverage |-> \"PASS\", abstraction_gap |-> \"pending\"]",
        "correctionInvoked": "[artifacts |-> FALSE, coverage |-> FALSE, abstraction_gap |-> FALSE]",
        "summaryStatus": "\"pending\"",
        "pc": "[orch |-> \"SelectPass\"]",
        "autoFix": "TRUE"
      }
    },
    {
      "state_num": 7,
      "label": "SelectPass",
      "vars": {
        "verdict": "[artifacts |-> \"PASS\", coverage |-> \"PASS\", abstraction_gap |-> \"FAIL\"]",
        "correctionInvoked": "[artifacts |-> FALSE, coverage |-> FALSE, abstraction_gap |-> TRUE]",
        "summaryStatus": "\"pending\"",
        "pc": "[orch |-> \"OrchestratorStart\"]",
        "autoFix": "TRUE"
      }
    },
    {
      "state_num": 8,
      "label": "OrchestratorStart",
      "vars": {
        "verdict": "[artifacts |-> \"PASS\", coverage |-> \"PASS\", abstraction_gap |-> \"FAIL\"]",
        "correctionInvoked": "[artifacts |-> FALSE, coverage |-> FALSE, abstraction_gap |-> TRUE]",
        "summaryStatus": "\"pending\"",
        "pc": "[orch |-> \"ComputeSummary\"]",
        "autoFix": "TRUE"
      }
    },
    {
      "state_num": 9,
      "label": "ComputeSummary",
      "vars": {
        "verdict": "[artifacts |-> \"PASS\", coverage |-> \"PASS\", abstraction_gap |-> \"FAIL\"]",
        "correctionInvoked": "[artifacts |-> FALSE, coverage |-> FALSE, abstraction_gap |-> TRUE]",
        "summaryStatus": "\"fail\"",
        "pc": "[orch |-> \"Finish\"]",
        "autoFix": "TRUE"
      }
    },
    {
      "state_num": 10,
      "label": "Finish",
      "vars": {
        "verdict": "[artifacts |-> \"PASS\", coverage |-> \"PASS\", abstraction_gap |-> \"FAIL\"]",
        "correctionInvoked": "[artifacts |-> FALSE, coverage |-> FALSE, abstraction_gap |-> TRUE]",
        "summaryStatus": "\"fail\"",
        "pc": "[orch |-> \"Done\"]",
        "autoFix": "TRUE"
      }
    }
  ],
  [
    {
      "state_num": 1,
      "label": "Init",
      "vars": {
        "verdict": "[artifacts |-> \"pending\", coverage |-> \"pending\", abstraction_gap |-> \"pending\"]",
        "correctionInvoked": "[artifacts |-> FALSE, coverage |-> FALSE, abstraction_gap |-> FALSE]",
        "summaryStatus": "\"pending\"",
        "pc": "[orch |-> \"OrchestratorStart\"]",
        "autoFix": "TRUE"
      }
    },
    {
      "state_num": 2,
      "label": "OrchestratorStart",
      "vars": {
        "verdict": "[artifacts |-> \"pending\", coverage |-> \"pending\", abstraction_gap |-> \"pending\"]",
        "correctionInvoked": "[artifacts |-> FALSE, coverage |-> FALSE, abstraction_gap |-> FALSE]",
        "summaryStatus": "\"pending\"",
        "pc": "[orch |-> \"SelectPass\"]",
        "autoFix": "TRUE"
      }
    },
    {
      "state_num": 3,
      "label": "SelectPass",
      "vars": {
        "verdict": "[artifacts |-> \"FAIL\", coverage |-> \"pending\", abstraction_gap |-> \"pending\"]",
        "correctionInvoked": "[artifacts |-> TRUE, coverage |-> FALSE, abstraction_gap |-> FALSE]",
        "summaryStatus": "\"pending\"",
        "pc": "[orch |-> \"OrchestratorStart\"]",
        "autoFix": "TRUE"
      }
    },
    {
      "state_num": 4,
      "label": "OrchestratorStart",
      "vars": {
        "verdict": "[artifacts |-> \"FAIL\", coverage |-> \"pending\", abstraction_gap |-> \"pending\"]",
        "correctionInvoked": "[artifacts |-> TRUE, coverage |-> FALSE, abstraction_gap |-> FALSE]",
        "summaryStatus": "\"pending\"",
        "pc": "[orch |-> \"ComputeSummary\"]",
        "autoFix": "TRUE"
      }
    },
    {
      "state_num": 5,
      "label": "ComputeSummary",
      "vars": {
        "verdict": "[artifacts |-> \"FAIL\", coverage |-> \"pending\", abstraction_gap |-> \"pending\"]",
        "correctionInvoked": "[artifacts |-> TRUE, coverage |-> FALSE, abstraction_gap |-> FALSE]",
        "summaryStatus": "\"fail\"",
        "pc": "[orch |-> \"Finish\"]",
        "autoFix": "TRUE"
      }
    },
    {
      "state_num": 6,
      "label": "Finish",
      "vars": {
        "verdict": "[artifacts |-> \"FAIL\", coverage |-> \"pending\", abstraction_gap |-> \"pending\"]",
        "correctionInvoked": "[artifacts |-> TRUE, coverage |-> FALSE, abstraction_gap |-> FALSE]",
        "summaryStatus": "\"fail\"",
        "pc": "[orch |-> \"Done\"]",
        "autoFix": "TRUE"
      }
    }
  ],
  [
    {
      "state_num": 1,
      "label": "Init",
      "vars": {
        "verdict": "[artifacts |-> \"pending\", coverage |-> \"pending\", abstraction_gap |-> \"pending\"]",
        "correctionInvoked": "[artifacts |-> FALSE, coverage |-> FALSE, abstraction_gap |-> FALSE]",
        "summaryStatus": "\"pending\"",
        "pc": "[orch |-> \"OrchestratorStart\"]",
        "autoFix": "TRUE"
      }
    },
    {
      "state_num": 2,
      "label": "OrchestratorStart",
      "vars": {
        "verdict": "[artifacts |-> \"pending\", coverage |-> \"pending\", abstraction_gap |-> \"pending\"]",
        "correctionInvoked": "[artifacts |-> FALSE, coverage |-> FALSE, abstraction_gap |-> FALSE]",
        "summaryStatus": "\"pending\"",
        "pc": "[orch |-> \"SelectPass\"]",
        "autoFix": "TRUE"
      }
    },
    {
      "state_num": 3,
      "label": "SelectPass",
      "vars": {
        "verdict": "[artifacts |-> \"WARNING\", coverage |-> \"pending\", abstraction_gap |-> \"pending\"]",
        "correctionInvoked": "[artifacts |-> FALSE, coverage |-> FALSE, abstraction_gap |-> FALSE]",
        "summaryStatus": "\"pending\"",
        "pc": "[orch |-> \"OrchestratorStart\"]",
        "autoFix": "TRUE"
      }
    },
    {
      "state_num": 4,
      "label": "OrchestratorStart",
      "vars": {
        "verdict": "[artifacts |-> \"WARNING\", coverage |-> \"pending\", abstraction_gap |-> \"pending\"]",
        "correctionInvoked": "[artifacts |-> FALSE, coverage |-> FALSE, abstraction_gap |-> FALSE]",
        "summaryStatus": "\"pending\"",
        "pc": "[orch |-> \"SelectPass\"]",
        "autoFix": "TRUE"
      }
    },
    {
      "state_num": 5,
      "label": "SelectPass",
      "vars": {
        "verdict": "[artifacts |-> \"WARNING\", coverage |-> \"PASS\", abstraction_gap |-> \"pending\"]",
        "correctionInvoked": "[artifacts |-> FALSE, coverage |-> FALSE, abstraction_gap |-> FALSE]",
        "summaryStatus": "\"pending\"",
        "pc": "[orch |-> \"OrchestratorStart\"]",
        "autoFix": "TRUE"
      }
    },
    {
      "state_num": 6,
      "label": "OrchestratorStart",
      "vars": {
        "verdict": "[artifacts |-> \"WARNING\", coverage |-> \"PASS\", abstraction_gap |-> \"pending\"]",
        "correctionInvoked": "[artifacts |-> FALSE, coverage |-> FALSE, abstraction_gap |-> FALSE]",
        "summaryStatus": "\"pending\"",
        "pc": "[orch |-> \"SelectPass\"]",
        "autoFix": "TRUE"
      }
    },
    {
      "state_num": 7,
      "label": "SelectPass",
      "vars": {
        "verdict": "[artifacts |-> \"WARNING\", coverage |-> \"PASS\", abstraction_gap |-> \"WARNING\"]",
        "correctionInvoked": "[artifacts |-> FALSE, coverage |-> FALSE, abstraction_gap |-> FALSE]",
        "summaryStatus": "\"pending\"",
        "pc": "[orch |-> \"OrchestratorStart\"]",
        "autoFix": "TRUE"
      }
    },
    {
      "state_num": 8,
      "label": "OrchestratorStart",
      "vars": {
        "verdict": "[artifacts |-> \"WARNING\", coverage |-> \"PASS\", abstraction_gap |-> \"WARNING\"]",
        "correctionInvoked": "[artifacts |-> FALSE, coverage |-> FALSE, abstraction_gap |-> FALSE]",
        "summaryStatus": "\"pending\"",
        "pc": "[orch |-> \"ComputeSummary\"]",
        "autoFix": "TRUE"
      }
    },
    {
      "state_num": 9,
      "label": "ComputeSummary",
      "vars": {
        "verdict": "[artifacts |-> \"WARNING\", coverage |-> \"PASS\", abstraction_gap |-> \"WARNING\"]",
        "correctionInvoked": "[artifacts |-> FALSE, coverage |-> FALSE, abstraction_gap |-> FALSE]",
        "summaryStatus": "\"warning\"",
        "pc": "[orch |-> \"Finish\"]",
        "autoFix": "TRUE"
      }
    },
    {
      "state_num": 10,
      "label": "Finish",
      "vars": {
        "verdict": "[artifacts |-> \"WARNING\", coverage |-> \"PASS\", abstraction_gap |-> \"WARNING\"]",
        "correctionInvoked": "[artifacts |-> FALSE, coverage |-> FALSE, abstraction_gap |-> FALSE]",
        "summaryStatus": "\"warning\"",
        "pc": "[orch |-> \"Done\"]",
        "autoFix": "TRUE"
      }
    }
  ]
]