[
  [
    {
      "state_num": 1,
      "label": "Init",
      "vars": {
        "cli_retries_value": "0",
        "orchestrator_retries": "0",
        "forwarded": "FALSE",
        "error_raised": "FALSE",
        "phase": "\"init\"",
        "pc": "[main |-> \"SetupAutoFix\"]",
        "cli_retries_omitted": "FALSE",
        "auto_fix": "FALSE",
        "parsed_max_retries": "0"
      }
    },
    {
      "state_num": 2,
      "label": "SetupAutoFix",
      "vars": {
        "cli_retries_value": "0",
        "orchestrator_retries": "0",
        "forwarded": "FALSE",
        "error_raised": "FALSE",
        "phase": "\"init\"",
        "pc": "[main |-> \"ChooseRetries\"]",
        "cli_retries_omitted": "FALSE",
        "auto_fix": "FALSE",
        "parsed_max_retries": "0"
      }
    },
    {
      "state_num": 3,
      "label": "ChooseRetries",
      "vars": {
        "cli_retries_value": "0",
        "orchestrator_retries": "0",
        "forwarded": "FALSE",
        "error_raised": "FALSE",
        "phase": "\"init\"",
        "pc": "[main |-> \"ParseMaxRetries\"]",
        "cli_retries_omitted": "TRUE",
        "auto_fix": "FALSE",
        "parsed_max_retries": "0"
      }
    },
    {
      "state_num": 4,
      "label": "ParseMaxRetries",
      "vars": {
        "cli_retries_value": "0",
        "orchestrator_retries": "0",
        "forwarded": "FALSE",
        "error_raised": "FALSE",
        "phase": "\"parsed\"",
        "pc": "[main |-> \"ValidateNonNegative\"]",
        "cli_retries_omitted": "TRUE",
        "auto_fix": "FALSE",
        "parsed_max_retries": "2"
      }
    },
    {
      "state_num": 5,
      "label": "ValidateNonNegative",
      "vars": {
        "cli_retries_value": "0",
        "orchestrator_retries": "0",
        "forwarded": "FALSE",
        "error_raised": "FALSE",
        "phase": "\"validated\"",
        "pc": "[main |-> \"ForwardToOrchestrator\"]",
        "cli_retries_omitted": "TRUE",
        "auto_fix": "FALSE",
        "parsed_max_retries": "2"
      }
    },
    {
      "state_num": 6,
      "label": "ForwardToOrchestrator",
      "vars": {
        "cli_retries_value": "0",
        "orchestrator_retries": "0",
        "forwarded": "FALSE",
        "error_raised": "FALSE",
        "phase": "\"complete\"",
        "pc": "[main |-> \"Terminate\"]",
        "cli_retries_omitted": "TRUE",
        "auto_fix": "FALSE",
        "parsed_max_retries": "2"
      }
    },
    {
      "state_num": 7,
      "label": "Terminate",
      "vars": {
        "cli_retries_value": "0",
        "orchestrator_retries": "0",
        "forwarded": "FALSE",
        "error_raised": "FALSE",
        "phase": "\"complete\"",
        "pc": "[main |-> \"Done\"]",
        "cli_retries_omitted": "TRUE",
        "auto_fix": "FALSE",
        "parsed_max_retries": "2"
      }
    }
  ],
  [
    {
      "state_num": 1,
      "label": "Init",
      "vars": {
        "cli_retries_value": "0",
        "orchestrator_retries": "0",
        "forwarded": "FALSE",
        "error_raised": "FALSE",
        "phase": "\"init\"",
        "pc": "[main |-> \"SetupAutoFix\"]",
        "cli_retries_omitted": "FALSE",
        "auto_fix": "FALSE",
        "parsed_max_retries": "0"
      }
    },
    {
      "state_num": 2,
      "label": "SetupAutoFix",
      "vars": {
        "cli_retries_value": "0",
        "orchestrator_retries": "0",
        "forwarded": "FALSE",
        "error_raised": "FALSE",
        "phase": "\"init\"",
        "pc": "[main |-> \"ChooseRetries\"]",
        "cli_retries_omitted": "FALSE",
        "auto_fix": "TRUE",
        "parsed_max_retries": "0"
      }
    },
    {
      "state_num": 3,
      "label": "ChooseRetries",
      "vars": {
        "cli_retries_value": "-1",
        "orchestrator_retries": "0",
        "forwarded": "FALSE",
        "error_raised": "FALSE",
        "phase": "\"init\"",
        "pc": "[main |-> \"ParseMaxRetries\"]",
        "cli_retries_omitted": "FALSE",
        "auto_fix": "TRUE",
        "parsed_max_retries": "0"
      }
    },
    {
      "state_num": 4,
      "label": "ParseMaxRetries",
      "vars": {
        "cli_retries_value": "-1",
        "orchestrator_retries": "0",
        "forwarded": "FALSE",
        "error_raised": "FALSE",
        "phase": "\"parsed\"",
        "pc": "[main |-> \"ValidateNonNegative\"]",
        "cli_retries_omitted": "FALSE",
        "auto_fix": "TRUE",
        "parsed_max_retries": "-1"
      }
    },
    {
      "state_num": 5,
      "label": "ValidateNonNegative",
      "vars": {
        "cli_retries_value": "-1",
        "orchestrator_retries": "0",
        "forwarded": "FALSE",
        "error_raised": "TRUE",
        "phase": "\"rejected\"",
        "pc": "[main |-> \"Terminate\"]",
        "cli_retries_omitted": "FALSE",
        "auto_fix": "TRUE",
        "parsed_max_retries": "-1"
      }
    },
    {
      "state_num": 6,
      "label": "Terminate",
      "vars": {
        "cli_retries_value": "-1",
        "orchestrator_retries": "0",
        "forwarded": "FALSE",
        "error_raised": "TRUE",
        "phase": "\"rejected\"",
        "pc": "[main |-> \"Done\"]",
        "cli_retries_omitted": "FALSE",
        "auto_fix": "TRUE",
        "parsed_max_retries": "-1"
      }
    }
  ],
  [
    {
      "state_num": 1,
      "label": "Init",
      "vars": {
        "cli_retries_value": "0",
        "orchestrator_retries": "0",
        "forwarded": "FALSE",
        "error_raised": "FALSE",
        "phase": "\"init\"",
        "pc": "[main |-> \"SetupAutoFix\"]",
        "cli_retries_omitted": "FALSE",
        "auto_fix": "FALSE",
        "parsed_max_retries": "0"
      }
    },
    {
      "state_num": 2,
      "label": "SetupAutoFix",
      "vars": {
        "cli_retries_value": "0",
        "orchestrator_retries": "0",
        "forwarded": "FALSE",
        "error_raised": "FALSE",
        "phase": "\"init\"",
        "pc": "[main |-> \"ChooseRetries\"]",
        "cli_retries_omitted": "FALSE",
        "auto_fix": "TRUE",
        "parsed_max_retries": "0"
      }
    },
    {
      "state_num": 3,
      "label": "ChooseRetries",
      "vars": {
        "cli_retries_value": "3",
        "orchestrator_retries": "0",
        "forwarded": "FALSE",
        "error_raised": "FALSE",
        "phase": "\"init\"",
        "pc": "[main |-> \"ParseMaxRetries\"]",
        "cli_retries_omitted": "FALSE",
        "auto_fix": "TRUE",
        "parsed_max_retries": "0"
      }
    },
    {
      "state_num": 4,
      "label": "ParseMaxRetries",
      "vars": {
        "cli_retries_value": "3",
        "orchestrator_retries": "0",
        "forwarded": "FALSE",
        "error_raised": "FALSE",
        "phase": "\"parsed\"",
        "pc": "[main |-> \"ValidateNonNegative\"]",
        "cli_retries_omitted": "FALSE",
        "auto_fix": "TRUE",
        "parsed_max_retries": "3"
      }
    },
    {
      "state_num": 5,
      "label": "ValidateNonNegative",
      "vars": {
        "cli_retries_value": "3",
        "orchestrator_retries": "0",
        "forwarded": "FALSE",
        "error_raised": "FALSE",
        "phase": "\"validated\"",
        "pc": "[main |-> \"ForwardToOrchestrator\"]",
        "cli_retries_omitted": "FALSE",
        "auto_fix": "TRUE",
        "parsed_max_retries": "3"
      }
    },
    {
      "state_num": 6,
      "label": "ForwardToOrchestrator",
      "vars": {
        "cli_retries_value": "3",
        "orchestrator_retries": "3",
        "forwarded": "TRUE",
        "error_raised": "FALSE",
        "phase": "\"forwarded\"",
        "pc": "[main |-> \"SetComplete\"]",
        "cli_retries_omitted": "FALSE",
        "auto_fix": "TRUE",
        "parsed_max_retries": "3"
      }
    },
    {
      "state_num": 7,
      "label": "SetComplete",
      "vars": {
        "cli_retries_value": "3",
        "orchestrator_retries": "3",
        "forwarded": "TRUE",
        "error_raised": "FALSE",
        "phase": "\"complete\"",
        "pc": "[main |-> \"Terminate\"]",
        "cli_retries_omitted": "FALSE",
        "auto_fix": "TRUE",
        "parsed_max_retries": "3"
      }
    },
    {
      "state_num": 8,
      "label": "Terminate",
      "vars": {
        "cli_retries_value": "3",
        "orchestrator_retries": "3",
        "forwarded": "TRUE",
        "error_raised": "FALSE",
        "phase": "\"complete\"",
        "pc": "[main |-> \"Done\"]",
        "cli_retries_omitted": "FALSE",
        "auto_fix": "TRUE",
        "parsed_max_retries": "3"
      }
    }
  ],
  [
    {
      "state_num": 1,
      "label": "Init",
      "vars": {
        "cli_retries_value": "0",
        "orchestrator_retries": "0",
        "forwarded": "FALSE",
        "error_raised": "FALSE",
        "phase": "\"init\"",
        "pc": "[main |-> \"SetupAutoFix\"]",
        "cli_retries_omitted": "FALSE",
        "auto_fix": "FALSE",
        "parsed_max_retries": "0"
      }
    },
    {
      "state_num": 2,
      "label": "SetupAutoFix",
      "vars": {
        "cli_retries_value": "0",
        "orchestrator_retries": "0",
        "forwarded": "FALSE",
        "error_raised": "FALSE",
        "phase": "\"init\"",
        "pc": "[main |-> \"ChooseRetries\"]",
        "cli_retries_omitted": "FALSE",
        "auto_fix": "TRUE",
        "parsed_max_retries": "0"
      }
    },
    {
      "state_num": 3,
      "label": "ChooseRetries",
      "vars": {
        "cli_retries_value": "0",
        "orchestrator_retries": "0",
        "forwarded": "FALSE",
        "error_raised": "FALSE",
        "phase": "\"init\"",
        "pc": "[main |-> \"ParseMaxRetries\"]",
        "cli_retries_omitted": "TRUE",
        "auto_fix": "TRUE",
        "parsed_max_retries": "0"
      }
    },
    {
      "state_num": 4,
      "label": "ParseMaxRetries",
      "vars": {
        "cli_retries_value": "0",
        "orchestrator_retries": "0",
        "forwarded": "FALSE",
        "error_raised": "FALSE",
        "phase": "\"parsed\"",
        "pc": "[main |-> \"ValidateNonNegative\"]",
        "cli_retries_omitted": "TRUE",
        "auto_fix": "TRUE",
        "parsed_max_retries": "2"
      }
    },
    {
      "state_num": 5,
      "label": "ValidateNonNegative",
      "vars": {
        "cli_retries_value": "0",
        "orchestrator_retries": "0",
        "forwarded": "FALSE",
        "error_raised": "FALSE",
        "phase": "\"validated\"",
        "pc": "[main |-> \"ForwardToOrchestrator\"]",
        "cli_retries_omitted": "TRUE",
        "auto_fix": "TRUE",
        "parsed_max_retries": "2"
      }
    },
    {
      "state_num": 6,
      "label": "ForwardToOrchestrator",
      "vars": {
        "cli_retries_value": "0",
        "orchestrator_retries": "2",
        "forwarded": "TRUE",
        "error_raised": "FALSE",
        "phase": "\"forwarded\"",
        "pc": "[main |-> \"SetComplete\"]",
        "cli_retries_omitted": "TRUE",
        "auto_fix": "TRUE",
        "parsed_max_retries": "2"
      }
    },
    {
      "state_num": 7,
      "label": "SetComplete",
      "vars": {
        "cli_retries_value": "0",
        "orchestrator_retries": "2",
        "forwarded": "TRUE",
        "error_raised": "FALSE",
        "phase": "\"complete\"",
        "pc": "[main |-> \"Terminate\"]",
        "cli_retries_omitted": "TRUE",
        "auto_fix": "TRUE",
        "parsed_max_retries": "2"
      }
    },
    {
      "state_num": 8,
      "label": "Terminate",
      "vars": {
        "cli_retries_value": "0",
        "orchestrator_retries": "2",
        "forwarded": "TRUE",
        "error_raised": "FALSE",
        "phase": "\"complete\"",
        "pc": "[main |-> \"Done\"]",
        "cli_retries_omitted": "TRUE",
        "auto_fix": "TRUE",
        "parsed_max_retries": "2"
      }
    }
  ],
  [
    {
      "state_num": 1,
      "label": "Init",
      "vars": {
        "cli_retries_value": "0",
        "orchestrator_retries": "0",
        "forwarded": "FALSE",
        "error_raised": "FALSE",
        "phase": "\"init\"",
        "pc": "[main |-> \"SetupAutoFix\"]",
        "cli_retries_omitted": "FALSE",
        "auto_fix": "FALSE",
        "parsed_max_retries": "0"
      }
    },
    {
      "state_num": 2,
      "label": "SetupAutoFix",
      "vars": {
        "cli_retries_value": "0",
        "orchestrator_retries": "0",
        "forwarded": "FALSE",
        "error_raised": "FALSE",
        "phase": "\"init\"",
        "pc": "[main |-> \"ChooseRetries\"]",
        "cli_retries_omitted": "FALSE",
        "auto_fix": "TRUE",
        "parsed_max_retries": "0"
      }
    },
    {
      "state_num": 3,
      "label": "ChooseRetries",
      "vars": {
        "cli_retries_value": "0",
        "orchestrator_retries": "0",
        "forwarded": "FALSE",
        "error_raised": "FALSE",
        "phase": "\"init\"",
        "pc": "[main |-> \"ParseMaxRetries\"]",
        "cli_retries_omitted": "FALSE",
        "auto_fix": "TRUE",
        "parsed_max_retries": "0"
      }
    },
    {
      "state_num": 4,
      "label": "ParseMaxRetries",
      "vars": {
        "cli_retries_value": "0",
        "orchestrator_retries": "0",
        "forwarded": "FALSE",
        "error_raised": "FALSE",
        "phase": "\"parsed\"",
        "pc": "[main |-> \"ValidateNonNegative\"]",
        "cli_retries_omitted": "FALSE",
        "auto_fix": "TRUE",
        "parsed_max_retries": "0"
      }
    },
    {
      "state_num": 5,
      "label": "ValidateNonNegative",
      "vars": {
        "cli_retries_value": "0",
        "orchestrator_retries": "0",
        "forwarded": "FALSE",
        "error_raised": "FALSE",
        "phase": "\"validated\"",
        "pc": "[main |-> \"ForwardToOrchestrator\"]",
        "cli_retries_omitted": "FALSE",
        "auto_fix": "TRUE",
        "parsed_max_retries": "0"
      }
    },
    {
      "state_num": 6,
      "label": "ForwardToOrchestrator",
      "vars": {
        "cli_retries_value": "0",
        "orchestrator_retries": "0",
        "forwarded": "TRUE",
        "error_raised": "FALSE",
        "phase": "\"forwarded\"",
        "pc": "[main |-> \"SetComplete\"]",
        "cli_retries_omitted": "FALSE",
        "auto_fix": "TRUE",
        "parsed_max_retries": "0"
      }
    },
    {
      "state_num": 7,
      "label": "SetComplete",
      "vars": {
        "cli_retries_value": "0",
        "orchestrator_retries": "0",
        "forwarded": "TRUE",
        "error_raised": "FALSE",
        "phase": "\"complete\"",
        "pc": "[main |-> \"Terminate\"]",
        "cli_retries_omitted": "FALSE",
        "auto_fix": "TRUE",
        "parsed_max_retries": "0"
      }
    },
    {
      "state_num": 8,
      "label": "Terminate",
      "vars": {
        "cli_retries_value": "0",
        "orchestrator_retries": "0",
        "forwarded": "TRUE",
        "error_raised": "FALSE",
        "phase": "\"complete\"",
        "pc": "[main |-> \"Done\"]",
        "cli_retries_omitted": "FALSE",
        "auto_fix": "TRUE",
        "parsed_max_retries": "0"
      }
    }
  ],
  [
    {
      "state_num": 1,
      "label": "Init",
      "vars": {
        "cli_retries_value": "0",
        "orchestrator_retries": "0",
        "forwarded": "FALSE",
        "error_raised": "FALSE",
        "phase": "\"init\"",
        "pc": "[main |-> \"SetupAutoFix\"]",
        "cli_retries_omitted": "FALSE",
        "auto_fix": "FALSE",
        "parsed_max_retries": "0"
      }
    },
    {
      "state_num": 2,
      "label": "SetupAutoFix",
      "vars": {
        "cli_retries_value": "0",
        "orchestrator_retries": "0",
        "forwarded": "FALSE",
        "error_raised": "FALSE",
        "phase": "\"init\"",
        "pc": "[main |-> \"ChooseRetries\"]",
        "cli_retries_omitted": "FALSE",
        "auto_fix": "FALSE",
        "parsed_max_retries": "0"
      }
    },
    {
      "state_num": 3,
      "label": "ChooseRetries",
      "vars": {
        "cli_retries_value": "0",
        "orchestrator_retries": "0",
        "forwarded": "FALSE",
        "error_raised": "FALSE",
        "phase": "\"init\"",
        "pc": "[main |-> \"ParseMaxRetries\"]",
        "cli_retries_omitted": "FALSE",
        "auto_fix": "FALSE",
        "parsed_max_retries": "0"
      }
    },
    {
      "state_num": 4,
      "label": "ParseMaxRetries",
      "vars": {
        "cli_retries_value": "0",
        "orchestrator_retries": "0",
        "forwarded": "FALSE",
        "error_raised": "FALSE",
        "phase": "\"parsed\"",
        "pc": "[main |-> \"ValidateNonNegative\"]",
        "cli_retries_omitted": "FALSE",
        "auto_fix": "FALSE",
        "parsed_max_retries": "0"
      }
    },
    {
      "state_num": 5,
      "label": "ValidateNonNegative",
      "vars": {
        "cli_retries_value": "0",
        "orchestrator_retries": "0",
        "forwarded": "FALSE",
        "error_raised": "FALSE",
        "phase": "\"validated\"",
        "pc": "[main |-> \"ForwardToOrchestrator\"]",
        "cli_retries_omitted": "FALSE",
        "auto_fix": "FALSE",
        "parsed_max_retries": "0"
      }
    },
    {
      "state_num": 6,
      "label": "ForwardToOrchestrator",
      "vars": {
        "cli_retries_value": "0",
        "orchestrator_retries": "0",
        "forwarded": "FALSE",
        "error_raised": "FALSE",
        "phase": "\"complete\"",
        "pc": "[main |-> \"Terminate\"]",
        "cli_retries_omitted": "FALSE",
        "auto_fix": "FALSE",
        "parsed_max_retries": "0"
      }
    },
    {
      "state_num": 7,
      "label": "Terminate",
      "vars": {
        "cli_retries_value": "0",
        "orchestrator_retries": "0",
        "forwarded": "FALSE",
        "error_raised": "FALSE",
        "phase": "\"complete\"",
        "pc": "[main |-> \"Done\"]",
        "cli_retries_omitted": "FALSE",
        "auto_fix": "FALSE",
        "parsed_max_retries": "0"
      }
    }
  ],
  [
    {
      "state_num": 1,
      "label": "Init",
      "vars": {
        "cli_retries_value": "0",
        "orchestrator_retries": "0",
        "forwarded": "FALSE",
        "error_raised": "FALSE",
        "phase": "\"init\"",
        "pc": "[main |-> \"SetupAutoFix\"]",
        "cli_retries_omitted": "FALSE",
        "auto_fix": "FALSE",
        "parsed_max_retries": "0"
      }
    },
    {
      "state_num": 2,
      "label": "SetupAutoFix",
      "vars": {
        "cli_retries_value": "0",
        "orchestrator_retries": "0",
        "forwarded": "FALSE",
        "error_raised": "FALSE",
        "phase": "\"init\"",
        "pc": "[main |-> \"ChooseRetries\"]",
        "cli_retries_omitted": "FALSE",
        "auto_fix": "FALSE",
        "parsed_max_retries": "0"
      }
    },
    {
      "state_num": 3,
      "label": "ChooseRetries",
      "vars": {
        "cli_retries_value": "0",
        "orchestrator_retries": "0",
        "forwarded": "FALSE",
        "error_raised": "FALSE",
        "phase": "\"init\"",
        "pc": "[main |-> \"ParseMaxRetries\"]",
        "cli_retries_omitted": "FALSE",
        "auto_fix": "FALSE",
        "parsed_max_retries": "0"
      }
    },
    {
      "state_num": 4,
      "label": "ParseMaxRetries",
      "vars": {
        "cli_retries_value": "0",
        "orchestrator_retries": "0",
        "forwarded": "FALSE",
        "error_raised": "FALSE",
        "phase": "\"parsed\"",
        "pc": "[main |-> \"ValidateNonNegative\"]",
        "cli_retries_omitted": "FALSE",
        "auto_fix": "FALSE",
        "parsed_max_retries": "0"
      }
    },
    {
      "state_num": 5,
      "label": "ValidateNonNegative",
      "vars": {
        "cli_retries_value": "0",
        "orchestrator_retries": "0",
        "forwarded": "FALSE",
        "error_raised": "FALSE",
        "phase": "\"validated\"",
        "pc": "[main |-> \"ForwardToOrchestrator\"]",
        "cli_retries_omitted": "FALSE",
        "auto_fix": "FALSE",
        "parsed_max_retries": "0"
      }
    },
    {
      "state_num": 6,
      "label": "ForwardToOrchestrator",
      "vars": {
        "cli_retries_value": "0",
        "orchestrator_retries": "0",
        "forwarded": "FALSE",
        "error_raised": "FALSE",
        "phase": "\"complete\"",
        "pc": "[main |-> \"Terminate\"]",
        "cli_retries_omitted": "FALSE",
        "auto_fix": "FALSE",
        "parsed_max_retries": "0"
      }
    },
    {
      "state_num": 7,
      "label": "Terminate",
      "vars": {
        "cli_retries_value": "0",
        "orchestrator_retries": "0",
        "forwarded": "FALSE",
        "error_raised": "FALSE",
        "phase": "\"complete\"",
        "pc": "[main |-> \"Done\"]",
        "cli_retries_omitted": "FALSE",
        "auto_fix": "FALSE",
        "parsed_max_retries": "0"
      }
    }
  ],
  [
    {
      "state_num": 1,
      "label": "Init",
      "vars": {
        "cli_retries_value": "0",
        "orchestrator_retries": "0",
        "forwarded": "FALSE",
        "error_raised": "FALSE",
        "phase": "\"init\"",
        "pc": "[main |-> \"SetupAutoFix\"]",
        "cli_retries_omitted": "FALSE",
        "auto_fix": "FALSE",
        "parsed_max_retries": "0"
      }
    },
    {
      "state_num": 2,
      "label": "SetupAutoFix",
      "vars": {
        "cli_retries_value": "0",
        "orchestrator_retries": "0",
        "forwarded": "FALSE",
        "error_raised": "FALSE",
        "phase": "\"init\"",
        "pc": "[main |-> \"ChooseRetries\"]",
        "cli_retries_omitted": "FALSE",
        "auto_fix": "FALSE",
        "parsed_max_retries": "0"
      }
    },
    {
      "state_num": 3,
      "label": "ChooseRetries",
      "vars": {
        "cli_retries_value": "1",
        "orchestrator_retries": "0",
        "forwarded": "FALSE",
        "error_raised": "FALSE",
        "phase": "\"init\"",
        "pc": "[main |-> \"ParseMaxRetries\"]",
        "cli_retries_omitted": "FALSE",
        "auto_fix": "FALSE",
        "parsed_max_retries": "0"
      }
    },
    {
      "state_num": 4,
      "label": "ParseMaxRetries",
      "vars": {
        "cli_retries_value": "1",
        "orchestrator_retries": "0",
        "forwarded": "FALSE",
        "error_raised": "FALSE",
        "phase": "\"parsed\"",
        "pc": "[main |-> \"ValidateNonNegative\"]",
        "cli_retries_omitted": "FALSE",
        "auto_fix": "FALSE",
        "parsed_max_retries": "1"
      }
    },
    {
      "state_num": 5,
      "label": "ValidateNonNegative",
      "vars": {
        "cli_retries_value": "1",
        "orchestrator_retries": "0",
        "forwarded": "FALSE",
        "error_raised": "FALSE",
        "phase": "\"validated\"",
        "pc": "[main |-> \"ForwardToOrchestrator\"]",
        "cli_retries_omitted": "FALSE",
        "auto_fix": "FALSE",
        "parsed_max_retries": "1"
      }
    },
    {
      "state_num": 6,
      "label": "ForwardToOrchestrator",
      "vars": {
        "cli_retries_value": "1",
        "orchestrator_retries": "0",
        "forwarded": "FALSE",
        "error_raised": "FALSE",
        "phase": "\"complete\"",
        "pc": "[main |-> \"Terminate\"]",
        "cli_retries_omitted": "FALSE",
        "auto_fix": "FALSE",
        "parsed_max_retries": "1"
      }
    },
    {
      "state_num": 7,
      "label": "Terminate",
      "vars": {
        "cli_retries_value": "1",
        "orchestrator_retries": "0",
        "forwarded": "FALSE",
        "error_raised": "FALSE",
        "phase": "\"complete\"",
        "pc": "[main |-> \"Done\"]",
        "cli_retries_omitted": "FALSE",
        "auto_fix": "FALSE",
        "parsed_max_retries": "1"
      }
    }
  ],
  [
    {
      "state_num": 1,
      "label": "Init",
      "vars": {
        "cli_retries_value": "0",
        "orchestrator_retries": "0",
        "forwarded": "FALSE",
        "error_raised": "FALSE",
        "phase": "\"init\"",
        "pc": "[main |-> \"SetupAutoFix\"]",
        "cli_retries_omitted": "FALSE",
        "auto_fix": "FALSE",
        "parsed_max_retries": "0"
      }
    },
    {
      "state_num": 2,
      "label": "SetupAutoFix",
      "vars": {
        "cli_retries_value": "0",
        "orchestrator_retries": "0",
        "forwarded": "FALSE",
        "error_raised": "FALSE",
        "phase": "\"init\"",
        "pc": "[main |-> \"ChooseRetries\"]",
        "cli_retries_omitted": "FALSE",
        "auto_fix": "TRUE",
        "parsed_max_retries": "0"
      }
    },
    {
      "state_num": 3,
      "label": "ChooseRetries",
      "vars": {
        "cli_retries_value": "0",
        "orchestrator_retries": "0",
        "forwarded": "FALSE",
        "error_raised": "FALSE",
        "phase": "\"init\"",
        "pc": "[main |-> \"ParseMaxRetries\"]",
        "cli_retries_omitted": "FALSE",
        "auto_fix": "TRUE",
        "parsed_max_retries": "0"
      }
    },
    {
      "state_num": 4,
      "label": "ParseMaxRetries",
      "vars": {
        "cli_retries_value": "0",
        "orchestrator_retries": "0",
        "forwarded": "FALSE",
        "error_raised": "FALSE",
        "phase": "\"parsed\"",
        "pc": "[main |-> \"ValidateNonNegative\"]",
        "cli_retries_omitted": "FALSE",
        "auto_fix": "TRUE",
        "parsed_max_retries": "0"
      }
    },
    {
      "state_num": 5,
      "label": "ValidateNonNegative",
      "vars": {
        "cli_retries_value": "0",
        "orchestrator_retries": "0",
        "forwarded": "FALSE",
        "error_raised": "FALSE",
        "phase": "\"validated\"",
        "pc": "[main |-> \"ForwardToOrchestrator\"]",
        "cli_retries_omitted": "FALSE",
        "auto_fix": "TRUE",
        "parsed_max_retries": "0"
      }
    },
    {
      "state_num": 6,
      "label": "ForwardToOrchestrator",
      "vars": {
        "cli_retries_value": "0",
        "orchestrator_retries": "0",
        "forwarded": "TRUE",
        "error_raised": "FALSE",
        "phase": "\"forwarded\"",
        "pc": "[main |-> \"SetComplete\"]",
        "cli_retries_omitted": "FALSE",
        "auto_fix": "TRUE",
        "parsed_max_retries": "0"
      }
    },
    {
      "state_num": 7,
      "label": "SetComplete",
      "vars": {
        "cli_retries_value": "0",
        "orchestrator_retries": "0",
        "forwarded": "TRUE",
        "error_raised": "FALSE",
        "phase": "\"complete\"",
        "pc": "[main |-> \"Terminate\"]",
        "cli_retries_omitted": "FALSE",
        "auto_fix": "TRUE",
        "parsed_max_retries": "0"
      }
    },
    {
      "state_num": 8,
      "label": "Terminate",
      "vars": {
        "cli_retries_value": "0",
        "orchestrator_retries": "0",
        "forwarded": "TRUE",
        "error_raised": "FALSE",
        "phase": "\"complete\"",
        "pc": "[main |-> \"Done\"]",
        "cli_retries_omitted": "FALSE",
        "auto_fix": "TRUE",
        "parsed_max_retries": "0"
      }
    }
  ],
  [
    {
      "state_num": 1,
      "label": "Init",
      "vars": {
        "cli_retries_value": "0",
        "orchestrator_retries": "0",
        "forwarded": "FALSE",
        "error_raised": "FALSE",
        "phase": "\"init\"",
        "pc": "[main |-> \"SetupAutoFix\"]",
        "cli_retries_omitted": "FALSE",
        "auto_fix": "FALSE",
        "parsed_max_retries": "0"
      }
    },
    {
      "state_num": 2,
      "label": "SetupAutoFix",
      "vars": {
        "cli_retries_value": "0",
        "orchestrator_retries": "0",
        "forwarded": "FALSE",
        "error_raised": "FALSE",
        "phase": "\"init\"",
        "pc": "[main |-> \"ChooseRetries\"]",
        "cli_retries_omitted": "FALSE",
        "auto_fix": "FALSE",
        "parsed_max_retries": "0"
      }
    },
    {
      "state_num": 3,
      "label": "ChooseRetries",
      "vars": {
        "cli_retries_value": "-1",
        "orchestrator_retries": "0",
        "forwarded": "FALSE",
        "error_raised": "FALSE",
        "phase": "\"init\"",
        "pc": "[main |-> \"ParseMaxRetries\"]",
        "cli_retries_omitted": "FALSE",
        "auto_fix": "FALSE",
        "parsed_max_retries": "0"
      }
    },
    {
      "state_num": 4,
      "label": "ParseMaxRetries",
      "vars": {
        "cli_retries_value": "-1",
        "orchestrator_retries": "0",
        "forwarded": "FALSE",
        "error_raised": "FALSE",
        "phase": "\"parsed\"",
        "pc": "[main |-> \"ValidateNonNegative\"]",
        "cli_retries_omitted": "FALSE",
        "auto_fix": "FALSE",
        "parsed_max_retries": "-1"
      }
    },
    {
      "state_num": 5,
      "label": "ValidateNonNegative",
      "vars": {
        "cli_retries_value": "-1",
        "orchestrator_retries": "0",
        "forwarded": "FALSE",
        "error_raised": "TRUE",
        "phase": "\"rejected\"",
        "pc": "[main |-> \"Terminate\"]",
        "cli_retries_omitted": "FALSE",
        "auto_fix": "FALSE",
        "parsed_max_retries": "-1"
      }
    },
    {
      "state_num": 6,
      "label": "Terminate",
      "vars": {
        "cli_retries_value": "-1",
        "orchestrator_retries": "0",
        "forwarded": "FALSE",
        "error_raised": "TRUE",
        "phase": "\"rejected\"",
        "pc": "[main |-> \"Done\"]",
        "cli_retries_omitted": "FALSE",
        "auto_fix": "FALSE",
        "parsed_max_retries": "-1"
      }
    }
  ]
]